<?xml version="1.0" encoding="utf-8"?>
<Return xmlns="http://www.irs.gov/efile" xmlns:xsi="http://www.w3.org/2001/XMLSchema-instance" returnVersion="2016v3.1">
  <ReturnHeader binaryAttachmentCnt="0">
    <ReturnTs>2019-06-27T14:06:43-05:00</ReturnTs>
    <TaxPeriodEndDt>2017-09-30</TaxPeriodEndDt>
    <PreparerFirmGrp>
      <PreparerFirmEIN>390843014</PreparerFirmEIN>
      <PreparerFirmName>
        <BusinessNameLine1Txt>KIECKHAFER DIETZLER HAUSER HANSON LLP</BusinessNameLine1Txt>
      </PreparerFirmName>
      <PreparerUSAddress>
        <AddressLine1Txt>PO BOX 637</AddressLine1Txt>
        <CityNm>WEST BEND</CityNm>
        <StateAbbreviationCd>WI</StateAbbreviationCd>
        <ZIPCd>530950637</ZIPCd>
      </PreparerUSAddress>
    </PreparerFirmGrp>
    <ReturnTypeCd>990PF</ReturnTypeCd>
    <TaxPeriodBeginDt>2016-10-01</TaxPeriodBeginDt>
    <Filer>
      <EIN>391497812</EIN>
      <BusinessName>
        <BusinessNameLine1Txt>HARTFORD HERITAGE INC</BusinessNameLine1Txt>
      </BusinessName>
      <BusinessNameControlTxt>HART</BusinessNameControlTxt>
      <PhoneNum>2626737999</PhoneNum>
      <USAddress>
        <AddressLine1Txt>147 N RURAL STREET</AddressLine1Txt>
        <CityNm>HARTFORD</CityNm>
        <StateAbbreviationCd>WI</StateAbbreviationCd>
        <ZIPCd>53027</ZIPCd>
      </USAddress>
    </Filer>
    <BusinessOfficerGrp>
      <PersonNm>RICK DIETZLER</PersonNm>
      <PersonTitleTxt>TREASURER</PersonTitleTxt>
      <PhoneNum>2626737999</PhoneNum>
      <SignatureDt>2019-06-05</SignatureDt>
      <DiscussWithPaidPreparerInd>true</DiscussWithPaidPreparerInd>
    </BusinessOfficerGrp>
    <PreparerPersonGrp>
      <PreparerPersonNm>JAMES SAUERESSIG</PreparerPersonNm>
      <PTIN>P00151912</PTIN>
      <PhoneNum>2623342341</PhoneNum>
      <PreparationDt>2019-06-05</PreparationDt>
    </PreparerPersonGrp>
    <FilingSecurityInformation>
      <AtSubmissionCreationDeviceId>169D93843940E8B709B89A6D81607ADEE0D54B43</AtSubmissionCreationDeviceId>
      <AtSubmissionFilingDeviceId>169D93843940E8B709B89A6D81607ADEE0D54B43</AtSubmissionFilingDeviceId>
    </FilingSecurityInformation>
    <TaxYr>2016</TaxYr>
    <BuildTS>2019-02-21 02:37:17Z</BuildTS>
  </ReturnHeader>
  <ReturnData documentCnt="12">
    <IRS990PF documentId="RetDoc3">
      <AmendedReturnInd>X</AmendedReturnInd>
      <Organization501c3ExemptPFInd>X</Organization501c3ExemptPFInd>
      <FMVAssetsEOYAmt>1907318</FMVAssetsEOYAmt>
      <MethodOfAccountingAccrualInd>X</MethodOfAccountingAccrualInd>
      <AnalysisOfRevenueAndExpenses>
        <ContriRcvdRevAndExpnssAmt>58382</ContriRcvdRevAndExpnssAmt>
        <InterestOnSavRevAndExpnssAmt>272</InterestOnSavRevAndExpnssAmt>
        <InterestOnSavNetInvstIncmAmt>272</InterestOnSavNetInvstIncmAmt>
        <InterestOnSavingsAdjNetIncmAmt>272</InterestOnSavingsAdjNetIncmAmt>
        <GrossRentsRevAndExpnssAmt>94803</GrossRentsRevAndExpnssAmt>
        <GrossRentsNetInvstIncmAmt>94803</GrossRentsNetInvstIncmAmt>
        <GrossRentsAdjNetIncmAmt>94803</GrossRentsAdjNetIncmAmt>
        <NetRentalIncomeOrLossAmt>94803</NetRentalIncomeOrLossAmt>
        <GrossSalesLessRetAndAllwncAmt>6128</GrossSalesLessRetAndAllwncAmt>
        <CostOfGoodsSoldAmt>3003</CostOfGoodsSoldAmt>
        <GrossProfitRevAndExpnssAmt referenceDocumentId="RetDoc12">3125</GrossProfitRevAndExpnssAmt>
        <GrossProfitAdjNetIncmAmt>3125</GrossProfitAdjNetIncmAmt>
        <OtherIncomeRevAndExpnssAmt referenceDocumentId="RetDoc11">68398</OtherIncomeRevAndExpnssAmt>
        <OtherIncomeAdjNetIncmAmt>68398</OtherIncomeAdjNetIncmAmt>
        <TotalRevAndExpnssAmt>224980</TotalRevAndExpnssAmt>
        <TotalNetInvstIncmAmt>95075</TotalNetInvstIncmAmt>
        <TotalAdjNetIncmAmt>166598</TotalAdjNetIncmAmt>
        <CompOfcrDirTrstRevAndExpnssAmt>37557</CompOfcrDirTrstRevAndExpnssAmt>
        <CompOfcrDirTrstAdjNetIncmAmt>37557</CompOfcrDirTrstAdjNetIncmAmt>
        <OthEmplSlrsWgsRevAndExpnssAmt>30471</OthEmplSlrsWgsRevAndExpnssAmt>
        <OthEmplSlrsWgsNetInvstIncmAmt>3000</OthEmplSlrsWgsNetInvstIncmAmt>
        <OthEmplSlrsWgsAdjNetIncmAmt>27471</OthEmplSlrsWgsAdjNetIncmAmt>
        <PensionEmplBnftRevAndExpnssAmt>4740</PensionEmplBnftRevAndExpnssAmt>
        <PensionEmplBnftNetInvstIncmAmt>230</PensionEmplBnftNetInvstIncmAmt>
        <PensionEmplBnftAdjNetIncmAmt>4510</PensionEmplBnftAdjNetIncmAmt>
        <AccountingFeesRevAndExpnssAmt referenceDocumentId="RetDoc4">2831</AccountingFeesRevAndExpnssAmt>
        <AccountingFeesNetInvstIncmAmt>283</AccountingFeesNetInvstIncmAmt>
        <AccountingFeesAdjNetIncmAmt>2548</AccountingFeesAdjNetIncmAmt>
        <TaxesRevAndExpnssAmt referenceDocumentId="RetDoc13">1648</TaxesRevAndExpnssAmt>
        <TaxesAdjNetIncmAmt>1648</TaxesAdjNetIncmAmt>
        <DeprecAndDpltnRevAndExpnssAmt referenceDocumentId="RetDoc5">40262</DeprecAndDpltnRevAndExpnssAmt>
        <DeprecAndDpltnNetInvstIncmAmt>11250</DeprecAndDpltnNetInvstIncmAmt>
        <DeprecAndDpltnAdjNetIncmAmt>29012</DeprecAndDpltnAdjNetIncmAmt>
        <OccupancyRevAndExpnssAmt>16982</OccupancyRevAndExpnssAmt>
        <OccupancyAdjNetIncmAmt>16982</OccupancyAdjNetIncmAmt>
        <TravConfMeetingRevAndExpnssAmt>2124</TravConfMeetingRevAndExpnssAmt>
        <TravConfMeetingAdjNetIncmAmt>2124</TravConfMeetingAdjNetIncmAmt>
        <OtherExpensesRevAndExpnssAmt referenceDocumentId="RetDoc9">38526</OtherExpensesRevAndExpnssAmt>
        <OtherExpensesNetInvstIncmAmt>2049</OtherExpensesNetInvstIncmAmt>
        <OtherExpensesAdjNetIncmAmt>36477</OtherExpensesAdjNetIncmAmt>
        <TotOprExpensesRevAndExpnssAmt>175141</TotOprExpensesRevAndExpnssAmt>
        <TotOprExpensesNetInvstIncmAmt>16812</TotOprExpensesNetInvstIncmAmt>
        <TotOprExpensesAdjNetIncmAmt>158329</TotOprExpensesAdjNetIncmAmt>
        <TotOprExpensesDsbrsChrtblAmt>0</TotOprExpensesDsbrsChrtblAmt>
        <ContriPaidRevAndExpnssAmt>0</ContriPaidRevAndExpnssAmt>
        <ContriPaidDsbrsChrtblAmt>0</ContriPaidDsbrsChrtblAmt>
        <TotalExpensesRevAndExpnssAmt>175141</TotalExpensesRevAndExpnssAmt>
        <TotalExpensesNetInvstIncmAmt>16812</TotalExpensesNetInvstIncmAmt>
        <TotalExpensesAdjNetIncmAmt>158329</TotalExpensesAdjNetIncmAmt>
        <TotalExpensesDsbrsChrtblAmt>0</TotalExpensesDsbrsChrtblAmt>
        <ExcessRevenueOverExpensesAmt>49839</ExcessRevenueOverExpensesAmt>
        <NetInvestmentIncomeAmt>78263</NetInvestmentIncomeAmt>
        <AdjustedNetIncomeAmt>8269</AdjustedNetIncomeAmt>
      </AnalysisOfRevenueAndExpenses>
      <Form990PFBalanceSheetsGrp>
        <CashBOYAmt>625</CashBOYAmt>
        <CashEOYAmt>1561</CashEOYAmt>
        <CashEOYFMVAmt>1561</CashEOYFMVAmt>
        <SavAndTempCashInvstBOYAmt>137435</SavAndTempCashInvstBOYAmt>
        <SavAndTempCashInvstEOYAmt>87005</SavAndTempCashInvstEOYAmt>
        <SavAndTempCashInvstEOYFMVAmt>87005</SavAndTempCashInvstEOYFMVAmt>
        <AcctRcvblAmt>1125</AcctRcvblAmt>
        <AcctRcvblBOYAmt>150</AcctRcvblBOYAmt>
        <AcctRcvblEOYAmt>1125</AcctRcvblEOYAmt>
        <AcctRcvblEOYFMVAmt>1125</AcctRcvblEOYFMVAmt>
        <InventoriesBOYAmt>12202</InventoriesBOYAmt>
        <InventoriesEOYAmt>12226</InventoriesEOYAmt>
        <InventoriesEOYFMVAmt>12226</InventoriesEOYFMVAmt>
        <CorporateStockEOYAmt referenceDocumentId="RetDoc6">100961</CorporateStockEOYAmt>
        <CorporateStockEOYFMVAmt>100961</CorporateStockEOYFMVAmt>
        <LandBldgEquipCostOrOtherBssAmt>1296065</LandBldgEquipCostOrOtherBssAmt>
        <LandBldgEquipAccumDeprecAmt>583725</LandBldgEquipAccumDeprecAmt>
        <LandBOYAmt>744602</LandBOYAmt>
        <LandEOYAmt referenceDocumentId="RetDoc7">712340</LandEOYAmt>
        <LandEOYFMVAmt>712340</LandEOYFMVAmt>
        <OtherAssetsBOYAmt referenceDocumentId="RetDoc8">961600</OtherAssetsBOYAmt>
        <OtherAssetsEOYAmt referenceDocumentId="RetDoc8">992100</OtherAssetsEOYAmt>
        <OtherAssetsEOYFMVAmt referenceDocumentId="RetDoc8">992100</OtherAssetsEOYFMVAmt>
        <TotalAssetsBOYAmt>1856614</TotalAssetsBOYAmt>
        <TotalAssetsEOYAmt>1907318</TotalAssetsEOYAmt>
        <TotalAssetsEOYFMVAmt>1907318</TotalAssetsEOYFMVAmt>
        <AccountsPayableBOYAmt>328</AccountsPayableBOYAmt>
        <AccountsPayableEOYAmt>416</AccountsPayableEOYAmt>
        <TotalLiabilitiesBOYAmt>328</TotalLiabilitiesBOYAmt>
        <TotalLiabilitiesEOYAmt>416</TotalLiabilitiesEOYAmt>
        <OrganizationFollowsSFAS117Ind>X</OrganizationFollowsSFAS117Ind>
        <UnrestrictedBOYAmt>1850183</UnrestrictedBOYAmt>
        <UnrestrictedEOYAmt>1897455</UnrestrictedEOYAmt>
        <TemporarilyRestrictedBOYAmt>6103</TemporarilyRestrictedBOYAmt>
        <TemporarilyRestrictedEOYAmt>9447</TemporarilyRestrictedEOYAmt>
        <TotNetAstOrFundBalancesBOYAmt>1856286</TotNetAstOrFundBalancesBOYAmt>
        <TotNetAstOrFundBalancesEOYAmt>1906902</TotNetAstOrFundBalancesEOYAmt>
        <TotalLiabilitiesNetAstBOYAmt>1856614</TotalLiabilitiesNetAstBOYAmt>
        <TotalLiabilitiesNetAstEOYAmt>1907318</TotalLiabilitiesNetAstEOYAmt>
      </Form990PFBalanceSheetsGrp>
      <ChgInNetAssetsFundBalancesGrp>
        <TotNetAstOrFundBalancesBOYAmt>1856286</TotNetAstOrFundBalancesBOYAmt>
        <ExcessRevenueOverExpensesAmt>49839</ExcessRevenueOverExpensesAmt>
        <OtherIncreasesAmt referenceDocumentId="RetDoc10">777</OtherIncreasesAmt>
        <SubtotalAmt>1906902</SubtotalAmt>
        <TotNetAstOrFundBalancesEOYAmt>1906902</TotNetAstOrFundBalancesEOYAmt>
      </ChgInNetAssetsFundBalancesGrp>
      <QlfyUndSect4940eReducedTaxGrp>
        <LiableSection4942TaxInd>false</LiableSection4942TaxInd>
        <AdjustedQlfyDistriYr1Amt>1500</AdjustedQlfyDistriYr1Amt>
        <NetVlNoncharitableAssetsYr1Amt>371246</NetVlNoncharitableAssetsYr1Amt>
        <DistributionYr1Rt>0.004040</DistributionYr1Rt>
        <AdjustedQlfyDistriYr2Amt>5882</AdjustedQlfyDistriYr2Amt>
        <NetVlNoncharitableAssetsYr2Amt>328918</NetVlNoncharitableAssetsYr2Amt>
        <DistributionYr2Rt>0.017883</DistributionYr2Rt>
        <AdjustedQlfyDistriYr3Amt>13676</AdjustedQlfyDistriYr3Amt>
        <NetVlNoncharitableAssetsYr3Amt>301636</NetVlNoncharitableAssetsYr3Amt>
        <DistributionYr3Rt>0.045339</DistributionYr3Rt>
        <AdjustedQlfyDistriYr4Amt>29832</AdjustedQlfyDistriYr4Amt>
        <NetVlNoncharitableAssetsYr4Amt>287320</NetVlNoncharitableAssetsYr4Amt>
        <DistributionYr4Rt>0.103828</DistributionYr4Rt>
        <AdjustedQlfyDistriYr5Amt>37769</AdjustedQlfyDistriYr5Amt>
        <NetVlNoncharitableAssetsYr5Amt>299983</NetVlNoncharitableAssetsYr5Amt>
        <DistributionYr5Rt>0.125904</DistributionYr5Rt>
        <TotalDistributionRt>0.296994</TotalDistributionRt>
        <AverageDistributionRt>0.059399</AverageDistributionRt>
        <NetVlNoncharitableAssetsAmt>480450</NetVlNoncharitableAssetsAmt>
        <AdjNetVlNoncharitableAssetsAmt>28538</AdjNetVlNoncharitableAssetsAmt>
        <NetInvestmentIncomePctAmt>783</NetInvestmentIncomePctAmt>
        <AdjNonchrtblNetInvstIncmPctAmt>29321</AdjNonchrtblNetInvstIncmPctAmt>
        <QualifyingDistributionsAmt>0</QualifyingDistributionsAmt>
      </QlfyUndSect4940eReducedTaxGrp>
      <ExciseTaxBasedOnInvstIncmGrp>
        <InvestmentIncomeExciseTaxAmt>1565</InvestmentIncomeExciseTaxAmt>
        <SubtotalAmt>1565</SubtotalAmt>
        <TaxBasedOnInvestmentIncomeAmt>1565</TaxBasedOnInvestmentIncomeAmt>
        <EstimatedPlusOvpmtIncmTxAmt>1640</EstimatedPlusOvpmtIncmTxAmt>
        <TotalPaymentsAndCreditsAmt>1565</TotalPaymentsAndCreditsAmt>
        <OriginalReturnOverpaymentAmt>-75</OriginalReturnOverpaymentAmt>
      </ExciseTaxBasedOnInvstIncmGrp>
      <StatementsRegardingActyGrp>
        <LegislativePoliticalActyInd>false</LegislativePoliticalActyInd>
        <MoreThan100SpentInd>false</MoreThan100SpentInd>
        <Form1120POLFiledInd>false</Form1120POLFiledInd>
        <ActivitiesNotPreviouslyRptInd>false</ActivitiesNotPreviouslyRptInd>
        <ChangesToArticlesOrBylawsInd>false</ChangesToArticlesOrBylawsInd>
        <UnrelatedBusIncmOverLimitInd>false</UnrelatedBusIncmOverLimitInd>
        <OrganizationDissolvedEtcInd>false</OrganizationDissolvedEtcInd>
        <Section508eRqrSatisfiedInd>true</Section508eRqrSatisfiedInd>
        <AtLeast5000InAssetsInd>true</AtLeast5000InAssetsInd>
        <Form990PFFiledWithAttyGenInd>true</Form990PFFiledWithAttyGenInd>
        <PrivateOperatingFoundationInd>true</PrivateOperatingFoundationInd>
        <NewSubstantialContributorsInd>false</NewSubstantialContributorsInd>
        <OwnControlledEntityInd>false</OwnControlledEntityInd>
        <DonorAdvisedFundInd>false</DonorAdvisedFundInd>
        <ComplyWithPublicInspRqrInd>true</ComplyWithPublicInspRqrInd>
        <WebsiteAddressTxt>WISCONSINAUTOMUSEUM.COM</WebsiteAddressTxt>
        <IndividualWithBooksNm>DAWN MUELLER</IndividualWithBooksNm>
        <PhoneNum>2626737999</PhoneNum>
        <LocationOfBooksUSAddress>
          <AddressLine1Txt>147 N RURAL STREET</AddressLine1Txt>
          <CityNm>HARTFORD</CityNm>
          <StateAbbreviationCd>WI</StateAbbreviationCd>
          <ZIPCd>53027</ZIPCd>
        </LocationOfBooksUSAddress>
        <ForeignAccountsQuestionInd>false</ForeignAccountsQuestionInd>
      </StatementsRegardingActyGrp>
      <StatementsRegardingActy4720Grp>
        <SaleOrExchDisqualifiedPrsnInd>false</SaleOrExchDisqualifiedPrsnInd>
        <BrrwOrLendDisqualifiedPrsnInd>false</BrrwOrLendDisqualifiedPrsnInd>
        <FurnGoodsDisqualifiedPrsnInd>false</FurnGoodsDisqualifiedPrsnInd>
        <PayCompDisqualifiedPrsnInd>false</PayCompDisqualifiedPrsnInd>
        <TransferAstDisqualifiedPrsnInd>false</TransferAstDisqualifiedPrsnInd>
        <PaymentToGovernmentOfficialInd>false</PaymentToGovernmentOfficialInd>
        <UndistributedIncomePYInd>false</UndistributedIncomePYInd>
        <BusinessHoldingsInd>false</BusinessHoldingsInd>
        <JeopardyInvestmentsInd>false</JeopardyInvestmentsInd>
        <UncorrectedPYJeopardyInvstInd>false</UncorrectedPYJeopardyInvstInd>
        <InfluenceLegislationInd>false</InfluenceLegislationInd>
        <InfluenceElectionInd>false</InfluenceElectionInd>
        <GrantsToIndividualsInd>false</GrantsToIndividualsInd>
        <GrantsToOrganizationsInd>false</GrantsToOrganizationsInd>
        <NoncharitablePurposeInd>false</NoncharitablePurposeInd>
        <RcvFndsToPayPrsnlBnftCntrctInd>false</RcvFndsToPayPrsnlBnftCntrctInd>
        <PayPremiumsPrsnlBnftCntrctInd>false</PayPremiumsPrsnlBnftCntrctInd>
        <ProhibitedTaxShelterTransInd>false</ProhibitedTaxShelterTransInd>
      </StatementsRegardingActy4720Grp>
      <OfficerDirTrstKeyEmplInfoGrp>
        <OfficerDirTrstKeyEmplGrp>
          <PersonNm>DAWN BONDHUS MUELLER</PersonNm>
          <USAddress>
            <AddressLine1Txt>147 N RURAL STREET</AddressLine1Txt>
            <CityNm>HARTFORD</CityNm>
            <StateAbbreviationCd>WI</StateAbbreviationCd>
            <ZIPCd>53027</ZIPCd>
          </USAddress>
          <TitleTxt>EXECUTIVE DI</TitleTxt>
          <AverageHrsPerWkDevotedToPosRt>40.00</AverageHrsPerWkDevotedToPosRt>
          <CompensationAmt>37557</CompensationAmt>
          <EmployeeBenefitProgramAmt>0</EmployeeBenefitProgramAmt>
          <ExpenseAccountOtherAllwncAmt>0</ExpenseAccountOtherAllwncAmt>
        </OfficerDirTrstKeyEmplGrp>
        <OfficerDirTrstKeyEmplGrp>
          <PersonNm>MICHAEL MALLY</PersonNm>
          <USAddress>
            <AddressLine1Txt>147 N RURAL STREET</AddressLine1Txt>
            <CityNm>HARTFORD</CityNm>
            <StateAbbreviationCd>WI</StateAbbreviationCd>
            <ZIPCd>53027</ZIPCd>
          </USAddress>
          <TitleTxt>PRESIDENT</TitleTxt>
          <AverageHrsPerWkDevotedToPosRt>1.00</AverageHrsPerWkDevotedToPosRt>
          <CompensationAmt>0</CompensationAmt>
          <EmployeeBenefitProgramAmt>0</EmployeeBenefitProgramAmt>
          <ExpenseAccountOtherAllwncAmt>0</ExpenseAccountOtherAllwncAmt>
        </OfficerDirTrstKeyEmplGrp>
        <OfficerDirTrstKeyEmplGrp>
          <PersonNm>DAVID LEFEBER</PersonNm>
          <USAddress>
            <AddressLine1Txt>147 N RURAL STREET</AddressLine1Txt>
            <CityNm>HARTFORD</CityNm>
            <StateAbbreviationCd>WI</StateAbbreviationCd>
            <ZIPCd>53027</ZIPCd>
          </USAddress>
          <TitleTxt>VICE PRESIDE</TitleTxt>
          <AverageHrsPerWkDevotedToPosRt>1.00</AverageHrsPerWkDevotedToPosRt>
          <CompensationAmt>0</CompensationAmt>
          <EmployeeBenefitProgramAmt>0</EmployeeBenefitProgramAmt>
          <ExpenseAccountOtherAllwncAmt>0</ExpenseAccountOtherAllwncAmt>
        </OfficerDirTrstKeyEmplGrp>
        <OfficerDirTrstKeyEmplGrp>
          <PersonNm>RICK DIETZLER</PersonNm>
          <USAddress>
            <AddressLine1Txt>147 N RURAL STREET</AddressLine1Txt>
            <CityNm>HARTFORD</CityNm>
            <StateAbbreviationCd>WI</StateAbbreviationCd>
            <ZIPCd>53027</ZIPCd>
          </USAddress>
          <TitleTxt>TREASURER</TitleTxt>
          <AverageHrsPerWkDevotedToPosRt>1.00</AverageHrsPerWkDevotedToPosRt>
          <CompensationAmt>0</CompensationAmt>
          <EmployeeBenefitProgramAmt>0</EmployeeBenefitProgramAmt>
          <ExpenseAccountOtherAllwncAmt>0</ExpenseAccountOtherAllwncAmt>
        </OfficerDirTrstKeyEmplGrp>
        <OfficerDirTrstKeyEmplGrp>
          <PersonNm>DOUG KISSEL</PersonNm>
          <USAddress>
            <AddressLine1Txt>147 N RURAL STREET</AddressLine1Txt>
            <CityNm>HARTFORD</CityNm>
            <StateAbbreviationCd>WI</StateAbbreviationCd>
            <ZIPCd>53027</ZIPCd>
          </USAddress>
          <TitleTxt>DIRECTOR</TitleTxt>
          <AverageHrsPerWkDevotedToPosRt>1.00</AverageHrsPerWkDevotedToPosRt>
          <CompensationAmt>0</CompensationAmt>
          <EmployeeBenefitProgramAmt>0</EmployeeBenefitProgramAmt>
          <ExpenseAccountOtherAllwncAmt>0</ExpenseAccountOtherAllwncAmt>
        </OfficerDirTrstKeyEmplGrp>
        <OfficerDirTrstKeyEmplGrp>
          <PersonNm>GEORGE BEYER</PersonNm>
          <USAddress>
            <AddressLine1Txt>147 N RURAL STREET</AddressLine1Txt>
            <CityNm>HARTFORD</CityNm>
            <StateAbbreviationCd>WI</StateAbbreviationCd>
            <ZIPCd>53027</ZIPCd>
          </USAddress>
          <TitleTxt>DIRECTOR</TitleTxt>
          <AverageHrsPerWkDevotedToPosRt>1.00</AverageHrsPerWkDevotedToPosRt>
          <CompensationAmt>0</CompensationAmt>
          <EmployeeBenefitProgramAmt>0</EmployeeBenefitProgramAmt>
          <ExpenseAccountOtherAllwncAmt>0</ExpenseAccountOtherAllwncAmt>
        </OfficerDirTrstKeyEmplGrp>
        <OfficerDirTrstKeyEmplGrp>
          <PersonNm>TIM PURMAN</PersonNm>
          <USAddress>
            <AddressLine1Txt>147 N RURAL STREET</AddressLine1Txt>
            <CityNm>HARTFORD</CityNm>
            <StateAbbreviationCd>WI</StateAbbreviationCd>
            <ZIPCd>53027</ZIPCd>
          </USAddress>
          <TitleTxt>DIRECTOR</TitleTxt>
          <AverageHrsPerWkDevotedToPosRt>1.00</AverageHrsPerWkDevotedToPosRt>
          <CompensationAmt>0</CompensationAmt>
          <EmployeeBenefitProgramAmt>0</EmployeeBenefitProgramAmt>
          <ExpenseAccountOtherAllwncAmt>0</ExpenseAccountOtherAllwncAmt>
        </OfficerDirTrstKeyEmplGrp>
        <OfficerDirTrstKeyEmplGrp>
          <PersonNm>PETER RASMUSSEN</PersonNm>
          <USAddress>
            <AddressLine1Txt>147 N RURAL STREET</AddressLine1Txt>
            <CityNm>HARTFORD</CityNm>
            <StateAbbreviationCd>WI</StateAbbreviationCd>
            <ZIPCd>53027</ZIPCd>
          </USAddress>
          <TitleTxt>DIRECTOR</TitleTxt>
          <AverageHrsPerWkDevotedToPosRt>1.00</AverageHrsPerWkDevotedToPosRt>
          <CompensationAmt>0</CompensationAmt>
          <EmployeeBenefitProgramAmt>0</EmployeeBenefitProgramAmt>
          <ExpenseAccountOtherAllwncAmt>0</ExpenseAccountOtherAllwncAmt>
        </OfficerDirTrstKeyEmplGrp>
        <OfficerDirTrstKeyEmplGrp>
          <PersonNm>TOM HOSTAD</PersonNm>
          <USAddress>
            <AddressLine1Txt>147 N RURAL STREET</AddressLine1Txt>
            <CityNm>HARTFORD</CityNm>
            <StateAbbreviationCd>WI</StateAbbreviationCd>
            <ZIPCd>53027</ZIPCd>
          </USAddress>
          <TitleTxt>DIRECTOR</TitleTxt>
          <AverageHrsPerWkDevotedToPosRt>1.00</AverageHrsPerWkDevotedToPosRt>
          <CompensationAmt>0</CompensationAmt>
          <EmployeeBenefitProgramAmt>0</EmployeeBenefitProgramAmt>
          <ExpenseAccountOtherAllwncAmt>0</ExpenseAccountOtherAllwncAmt>
        </OfficerDirTrstKeyEmplGrp>
        <CompOfHghstPdEmplOrNONETxt>NONE</CompOfHghstPdEmplOrNONETxt>
        <CompOfHghstPdCntrctOrNONETxt>NONE</CompOfHghstPdCntrctOrNONETxt>
      </OfficerDirTrstKeyEmplInfoGrp>
      <SummaryOfDirectChrtblActyGrp>
        <Description1Txt>OPERATION OF AN AUTO MUSEUM.</Description1Txt>
        <Expenses1Amt>137628</Expenses1Amt>
      </SummaryOfDirectChrtblActyGrp>
      <SumOfProgramRelatedInvstGrp>
        <Description1Txt>N/A</Description1Txt>
      </SumOfProgramRelatedInvstGrp>
      <MinimumInvestmentReturnGrp>
        <AverageMonthlyFMVOfSecAmt>100240</AverageMonthlyFMVOfSecAmt>
        <AverageMonthlyCashBalancesAmt>137527</AverageMonthlyCashBalancesAmt>
        <FMVAllOtherNoncharitableAstAmt>250000</FMVAllOtherNoncharitableAstAmt>
        <TotalFMVOfUnusedAssetsAmt>487767</TotalFMVOfUnusedAssetsAmt>
        <AdjustedTotalFMVOfUnusedAstAmt>487767</AdjustedTotalFMVOfUnusedAstAmt>
        <CashDeemedCharitableAmt>7317</CashDeemedCharitableAmt>
        <NetVlNoncharitableAssetsAmt>480450</NetVlNoncharitableAssetsAmt>
        <MinimumInvestmentReturnAmt>24023</MinimumInvestmentReturnAmt>
      </MinimumInvestmentReturnGrp>
      <DistributableAmountGrp>
        <Sect4942j3j5FndtnAndFrgnOrgInd>X</Sect4942j3j5FndtnAndFrgnOrgInd>
      </DistributableAmountGrp>
      <QualifyingDistriPartXIIGrp>
        <ExpensesAndContributionsAmt>0</ExpensesAndContributionsAmt>
        <QualifyingDistributionsAmt>0</QualifyingDistributionsAmt>
      </QualifyingDistriPartXIIGrp>
      <PrivateOperatingFoundationsGrp>
        <Section4942j3Ind>X</Section4942j3Ind>
        <LessorAdjNetIncmMinInvstRetGrp>
          <CurrentYearAmt>8269</CurrentYearAmt>
          <TotalAmt>8269</TotalAmt>
        </LessorAdjNetIncmMinInvstRetGrp>
        <Pct85LessorAdjIncmOrMinRetGrp>
          <CurrentYearAmt>7029</CurrentYearAmt>
          <TotalAmt>7029</TotalAmt>
        </Pct85LessorAdjIncmOrMinRetGrp>
        <QualifyingDistributionsGrp>
          <Year1Amt>1500</Year1Amt>
          <Year2Amt>5882</Year2Amt>
          <Year3Amt>13676</Year3Amt>
          <TotalAmt>21058</TotalAmt>
        </QualifyingDistributionsGrp>
        <QualifyingDistriMadeDrtGrp>
          <Year1Amt>1500</Year1Amt>
          <Year2Amt>5882</Year2Amt>
          <Year3Amt>13676</Year3Amt>
          <TotalAmt>21058</TotalAmt>
        </QualifyingDistriMadeDrtGrp>
        <TotalAssetsGrp>
          <CurrentYearAmt>1907318</CurrentYearAmt>
          <Year1Amt>1856614</Year1Amt>
          <Year2Amt>2204419</Year2Amt>
          <Year3Amt>2156099</Year3Amt>
          <TotalAmt>8124450</TotalAmt>
        </TotalAssetsGrp>
        <TotalAssetsSect4942j3BiGrp>
          <CurrentYearAmt>1476015</CurrentYearAmt>
          <Year1Amt>1464840</Year1Amt>
          <Year2Amt>1828999</Year2Amt>
          <Year3Amt>1809444</Year3Amt>
          <TotalAmt>6579298</TotalAmt>
        </TotalAssetsSect4942j3BiGrp>
      </PrivateOperatingFoundationsGrp>
      <SupplementaryInformationGrp>
        <OnlyContriToPreselectedInd>X</OnlyContriToPreselectedInd>
      </SupplementaryInformationGrp>
      <AnalysisIncomeProducingActyGrp>
        <ProgramServiceRevPartVIIGrp>
          <Desc>ADMISSIONS &amp; TOURS</Desc>
          <RelatedOrExemptFunctionIncmAmt>62973</RelatedOrExemptFunctionIncmAmt>
        </ProgramServiceRevPartVIIGrp>
        <IntOnSavAndTempCashInvstGrp>
          <ExclusionCd>14</ExclusionCd>
          <ExclusionAmt>272</ExclusionAmt>
        </IntOnSavAndTempCashInvstGrp>
        <NetRntlIncmReNotDebtFincdProp>
          <ExclusionCd>16</ExclusionCd>
          <ExclusionAmt>94803</ExclusionAmt>
        </NetRntlIncmReNotDebtFincdProp>
        <GrossProfitLossSlsOfInvntryGrp>
          <RelatedOrExemptFunctionIncmAmt>3125</RelatedOrExemptFunctionIncmAmt>
        </GrossProfitLossSlsOfInvntryGrp>
        <OtherRevenueDescribedGrp>
          <Desc>MISCELLANEOUS</Desc>
          <ExclusionCd>1</ExclusionCd>
          <ExclusionAmt>5425</ExclusionAmt>
        </OtherRevenueDescribedGrp>
        <SubtotalsIncmProducingActyGrp>
          <ExclusionAmt>100500</ExclusionAmt>
          <RelatedOrExemptFunctionIncmAmt>66098</RelatedOrExemptFunctionIncmAmt>
        </SubtotalsIncmProducingActyGrp>
        <TotalIncomeProducingActyAmt>166598</TotalIncomeProducingActyAmt>
      </AnalysisIncomeProducingActyGrp>
      <RlnOfActyToAccomOfExmptPrpsGrp>
        <RlnOfActyToAccomOfExmptPrpsGrp>
          <LineNumberTxt>1A</LineNumberTxt>
          <RelationshipStatementTxt>ADMISSIONS &amp; TOURS TO EDUCATE THE PUBLIC ON AUTOMOBILES.</RelationshipStatementTxt>
        </RlnOfActyToAccomOfExmptPrpsGrp>
        <RlnOfActyToAccomOfExmptPrpsGrp>
          <LineNumberTxt>10</LineNumberTxt>
          <RelationshipStatementTxt>SALE OF NOVELTY AND SOUVENIR ITEMS GENERATE INCOME FOR THE RESTORATION OF ANTIQUE AUTOMOBILES.</RelationshipStatementTxt>
        </RlnOfActyToAccomOfExmptPrpsGrp>
      </RlnOfActyToAccomOfExmptPrpsGrp>
      <TrnsfrTransRlnNonchrtblEOGrp>
        <TrnsfrOfCashToNonchrtblEOInd>false</TrnsfrOfCashToNonchrtblEOInd>
        <TrnsfrOtherAssetNonchrtblEOInd>false</TrnsfrOtherAssetNonchrtblEOInd>
        <SalesOrExchangesOfAssetsInd>false</SalesOrExchangesOfAssetsInd>
        <PurchaseOfAssetsNonchrtblEOInd>false</PurchaseOfAssetsNonchrtblEOInd>
        <RentalOfFacilitiesOthAssetsInd>false</RentalOfFacilitiesOthAssetsInd>
        <ReimbursementArrangementsInd>false</ReimbursementArrangementsInd>
        <LoansOrLoanGuaranteesInd>false</LoansOrLoanGuaranteesInd>
        <PerformanceOfServicesEtcInd>false</PerformanceOfServicesEtcInd>
        <SharingOfFacilitiesEtcInd>false</SharingOfFacilitiesEtcInd>
        <RelationshipsNonchrtblEOInd>false</RelationshipsNonchrtblEOInd>
      </TrnsfrTransRlnNonchrtblEOGrp>
    </IRS990PF>
    <IRS990ScheduleB documentId="RetDoc1">
      <Organization501c3ExemptPFInd>X</Organization501c3ExemptPFInd>
      <GeneralRuleInd>X</GeneralRuleInd>
      <ContributorInformationGrp>
        <ContributorNum>1</ContributorNum>
        <ContributorBusinessName>
          <BusinessNameLine1Txt>HARTFORD COMMUNITY SERVICE INC</BusinessNameLine1Txt>
        </ContributorBusinessName>
        <ContributorUSAddress>
          <AddressLine1Txt>147 N RURAL STREET</AddressLine1Txt>
          <CityNm>HARTFORD</CityNm>
          <StateAbbreviationCd>WI</StateAbbreviationCd>
          <ZIPCd>53027</ZIPCd>
        </ContributorUSAddress>
        <TotalContributionsAmt>10000</TotalContributionsAmt>
        <PersonContributionInd>X</PersonContributionInd>
      </ContributorInformationGrp>
      <ContributorInformationGrp>
        <ContributorNum>2</ContributorNum>
        <ContributorPersonNm>STEVE GORDON</ContributorPersonNm>
        <ContributorUSAddress>
          <AddressLine1Txt>PO DRAWER 6550</AddressLine1Txt>
          <CityNm>THOMASVILLE</CityNm>
          <StateAbbreviationCd>GA</StateAbbreviationCd>
          <ZIPCd>31758</ZIPCd>
        </ContributorUSAddress>
        <TotalContributionsAmt>16000</TotalContributionsAmt>
        <NoncashContributionInd>X</NoncashContributionInd>
      </ContributorInformationGrp>
      <ContributorInformationGrp>
        <ContributorNum>3</ContributorNum>
        <ContributorPersonNm>GILBERT CATALANO</ContributorPersonNm>
        <ContributorUSAddress>
          <AddressLine1Txt>1005 BEACON ST NW</AddressLine1Txt>
          <CityNm>PALM BAY</CityNm>
          <StateAbbreviationCd>FL</StateAbbreviationCd>
          <ZIPCd>32907</ZIPCd>
        </ContributorUSAddress>
        <TotalContributionsAmt>7000</TotalContributionsAmt>
        <NoncashContributionInd>X</NoncashContributionInd>
      </ContributorInformationGrp>
      <ContributorInformationGrp>
        <ContributorNum>4</ContributorNum>
        <ContributorPersonNm>NATIONAL PRESERVATION FOUNDATION</ContributorPersonNm>
        <ContributorUSAddress>
          <AddressLine1Txt>5545 MARTIN RD</AddressLine1Txt>
          <CityNm>GREAT VALLEY</CityNm>
          <StateAbbreviationCd>NY</StateAbbreviationCd>
          <ZIPCd>14741</ZIPCd>
        </ContributorUSAddress>
        <TotalContributionsAmt>7500</TotalContributionsAmt>
        <NoncashContributionInd>X</NoncashContributionInd>
      </ContributorInformationGrp>
      <NonCashPropertyContributionGrp>
        <ContributorNum>2</ContributorNum>
        <NoncashPropertyDesc>1917 DODGE BROS TOURING CAR</NoncashPropertyDesc>
        <FairMarketValueAmt>16000</FairMarketValueAmt>
        <ReceivedDt>2016-12-28</ReceivedDt>
      </NonCashPropertyContributionGrp>
      <NonCashPropertyContributionGrp>
        <ContributorNum>3</ContributorNum>
        <NoncashPropertyDesc>1918 NASH QUAD TRUCK</NoncashPropertyDesc>
        <FairMarketValueAmt>7000</FairMarketValueAmt>
        <ReceivedDt>2017-01-11</ReceivedDt>
      </NonCashPropertyContributionGrp>
      <NonCashPropertyContributionGrp>
        <ContributorNum>4</ContributorNum>
        <NoncashPropertyDesc>1953 NASH STATESMAN</NoncashPropertyDesc>
        <FairMarketValueAmt>7500</FairMarketValueAmt>
        <ReceivedDt>2017-01-17</ReceivedDt>
      </NonCashPropertyContributionGrp>
    </IRS990ScheduleB>
    <AccountingFeesSchedule documentId="RetDoc4">
      <AccountingFeesDetail>
        <CategoryTxt>INDIRECT ACCOUNTING FEES</CategoryTxt>
        <Amt>2831</Amt>
        <NetInvestmentIncomeAmt>283</NetInvestmentIncomeAmt>
        <AdjustedNetIncomeAmt>2548</AdjustedNetIncomeAmt>
      </AccountingFeesDetail>
    </AccountingFeesSchedule>
    <DepreciationSchedule documentId="RetDoc5">
      <DepreciationPropertyGrp>
        <PropertyDesc>BUILDING</PropertyDesc>
        <AcquiredDt>1999-10-01</AcquiredDt>
        <CostOrOtherBasisAmt>900000</CostOrOtherBasisAmt>
        <PriorYearDepreciationAmt>381563</PriorYearDepreciationAmt>
        <ComputationMethodTxt>S/L</ComputationMethodTxt>
        <LifeRt>39.0000</LifeRt>
        <CurrentYearExpenseAmt>22500</CurrentYearExpenseAmt>
        <NetInvestmentIncomeAmt>11250</NetInvestmentIncomeAmt>
        <AdjustedNetIncomeAmt>11250</AdjustedNetIncomeAmt>
      </DepreciationPropertyGrp>
      <DepreciationPropertyGrp>
        <PropertyDesc>1985 EXPENDITURES</PropertyDesc>
        <AcquiredDt>1985-05-20</AcquiredDt>
        <CostOrOtherBasisAmt>6052</CostOrOtherBasisAmt>
        <PriorYearDepreciationAmt>5832</PriorYearDepreciationAmt>
        <LifeRt>19.0000</LifeRt>
      </DepreciationPropertyGrp>
      <DepreciationPropertyGrp>
        <PropertyDesc>EAST SIDE LUMBER</PropertyDesc>
        <AcquiredDt>1986-01-03</AcquiredDt>
        <CostOrOtherBasisAmt>212</CostOrOtherBasisAmt>
        <PriorYearDepreciationAmt>212</PriorYearDepreciationAmt>
        <LifeRt>19.0000</LifeRt>
      </DepreciationPropertyGrp>
      <DepreciationPropertyGrp>
        <PropertyDesc>CONCRETE WORK</PropertyDesc>
        <AcquiredDt>1986-01-08</AcquiredDt>
        <CostOrOtherBasisAmt>684</CostOrOtherBasisAmt>
        <PriorYearDepreciationAmt>681</PriorYearDepreciationAmt>
        <LifeRt>19.0000</LifeRt>
      </DepreciationPropertyGrp>
      <DepreciationPropertyGrp>
        <PropertyDesc>HEAT TAPE</PropertyDesc>
        <AcquiredDt>1986-02-12</AcquiredDt>
        <CostOrOtherBasisAmt>139</CostOrOtherBasisAmt>
        <PriorYearDepreciationAmt>137</PriorYearDepreciationAmt>
        <LifeRt>19.0000</LifeRt>
      </DepreciationPropertyGrp>
      <DepreciationPropertyGrp>
        <PropertyDesc>BURGLAR/FIRE ALARM</PropertyDesc>
        <AcquiredDt>1986-04-28</AcquiredDt>
        <CostOrOtherBasisAmt>2350</CostOrOtherBasisAmt>
        <PriorYearDepreciationAmt>2343</PriorYearDepreciationAmt>
        <LifeRt>19.0000</LifeRt>
      </DepreciationPropertyGrp>
      <DepreciationPropertyGrp>
        <PropertyDesc>TAPE &amp; LABOR</PropertyDesc>
        <AcquiredDt>1986-04-28</AcquiredDt>
        <CostOrOtherBasisAmt>185</CostOrOtherBasisAmt>
        <PriorYearDepreciationAmt>185</PriorYearDepreciationAmt>
        <LifeRt>19.0000</LifeRt>
      </DepreciationPropertyGrp>
      <DepreciationPropertyGrp>
        <PropertyDesc>SCHMIDTS-SUPPLIES</PropertyDesc>
        <AcquiredDt>1986-04-28</AcquiredDt>
        <CostOrOtherBasisAmt>186</CostOrOtherBasisAmt>
        <PriorYearDepreciationAmt>186</PriorYearDepreciationAmt>
        <LifeRt>19.0000</LifeRt>
      </DepreciationPropertyGrp>
      <DepreciationPropertyGrp>
        <PropertyDesc>BLACKS-SOD FRONT</PropertyDesc>
        <AcquiredDt>1986-04-28</AcquiredDt>
        <CostOrOtherBasisAmt>225</CostOrOtherBasisAmt>
        <PriorYearDepreciationAmt>224</PriorYearDepreciationAmt>
        <LifeRt>19.0000</LifeRt>
      </DepreciationPropertyGrp>
      <DepreciationPropertyGrp>
        <PropertyDesc>JORDAN ELEC</PropertyDesc>
        <AcquiredDt>1986-05-17</AcquiredDt>
        <CostOrOtherBasisAmt>176</CostOrOtherBasisAmt>
        <PriorYearDepreciationAmt>173</PriorYearDepreciationAmt>
        <LifeRt>19.0000</LifeRt>
      </DepreciationPropertyGrp>
      <DepreciationPropertyGrp>
        <PropertyDesc>CITY-PAINT PKG LOT</PropertyDesc>
        <AcquiredDt>1986-03-08</AcquiredDt>
        <CostOrOtherBasisAmt>78</CostOrOtherBasisAmt>
        <PriorYearDepreciationAmt>76</PriorYearDepreciationAmt>
        <LifeRt>19.0000</LifeRt>
      </DepreciationPropertyGrp>
      <DepreciationPropertyGrp>
        <PropertyDesc>GRANDOWS-LOCKS</PropertyDesc>
        <AcquiredDt>1986-05-08</AcquiredDt>
        <CostOrOtherBasisAmt>155</CostOrOtherBasisAmt>
        <PriorYearDepreciationAmt>152</PriorYearDepreciationAmt>
        <LifeRt>19.0000</LifeRt>
      </DepreciationPropertyGrp>
      <DepreciationPropertyGrp>
        <PropertyDesc>CONTRACTS-HHH PAID</PropertyDesc>
        <AcquiredDt>1986-09-30</AcquiredDt>
        <CostOrOtherBasisAmt>77884</CostOrOtherBasisAmt>
        <PriorYearDepreciationAmt>77613</PriorYearDepreciationAmt>
        <LifeRt>19.0000</LifeRt>
      </DepreciationPropertyGrp>
      <DepreciationPropertyGrp>
        <PropertyDesc>UNIT HEATER</PropertyDesc>
        <AcquiredDt>1987-05-26</AcquiredDt>
        <CostOrOtherBasisAmt>655</CostOrOtherBasisAmt>
        <PriorYearDepreciationAmt>611</PriorYearDepreciationAmt>
        <ComputationMethodTxt>S/L</ComputationMethodTxt>
        <LifeRt>31.5000</LifeRt>
        <CurrentYearExpenseAmt>21</CurrentYearExpenseAmt>
        <AdjustedNetIncomeAmt>21</AdjustedNetIncomeAmt>
      </DepreciationPropertyGrp>
      <DepreciationPropertyGrp>
        <PropertyDesc>ENTRANCE SIGN</PropertyDesc>
        <AcquiredDt>1987-05-26</AcquiredDt>
        <CostOrOtherBasisAmt>225</CostOrOtherBasisAmt>
        <PriorYearDepreciationAmt>209</PriorYearDepreciationAmt>
        <ComputationMethodTxt>S/L</ComputationMethodTxt>
        <LifeRt>31.5000</LifeRt>
        <CurrentYearExpenseAmt>8</CurrentYearExpenseAmt>
        <AdjustedNetIncomeAmt>8</AdjustedNetIncomeAmt>
      </DepreciationPropertyGrp>
      <DepreciationPropertyGrp>
        <PropertyDesc>CONCRETE- LONG BLD</PropertyDesc>
        <AcquiredDt>1987-09-02</AcquiredDt>
        <CostOrOtherBasisAmt>414</CostOrOtherBasisAmt>
        <PriorYearDepreciationAmt>381</PriorYearDepreciationAmt>
        <ComputationMethodTxt>S/L</ComputationMethodTxt>
        <LifeRt>31.5000</LifeRt>
        <CurrentYearExpenseAmt>14</CurrentYearExpenseAmt>
        <AdjustedNetIncomeAmt>14</AdjustedNetIncomeAmt>
      </DepreciationPropertyGrp>
      <DepreciationPropertyGrp>
        <PropertyDesc>BEAMS</PropertyDesc>
        <AcquiredDt>1987-09-02</AcquiredDt>
        <CostOrOtherBasisAmt>2100</CostOrOtherBasisAmt>
        <PriorYearDepreciationAmt>1673</PriorYearDepreciationAmt>
        <ComputationMethodTxt>S/L</ComputationMethodTxt>
        <LifeRt>31.5000</LifeRt>
        <CurrentYearExpenseAmt>67</CurrentYearExpenseAmt>
        <AdjustedNetIncomeAmt>67</AdjustedNetIncomeAmt>
      </DepreciationPropertyGrp>
      <DepreciationPropertyGrp>
        <PropertyDesc>BUILDING IMP</PropertyDesc>
        <AcquiredDt>2000-09-30</AcquiredDt>
        <CostOrOtherBasisAmt>106083</CostOrOtherBasisAmt>
        <PriorYearDepreciationAmt>19041</PriorYearDepreciationAmt>
        <ComputationMethodTxt>S/L</ComputationMethodTxt>
        <LifeRt>39.0000</LifeRt>
        <CurrentYearExpenseAmt>2720</CurrentYearExpenseAmt>
        <AdjustedNetIncomeAmt>2720</AdjustedNetIncomeAmt>
      </DepreciationPropertyGrp>
      <DepreciationPropertyGrp>
        <PropertyDesc>VACUUM</PropertyDesc>
        <AcquiredDt>1985-01-21</AcquiredDt>
        <CostOrOtherBasisAmt>63</CostOrOtherBasisAmt>
        <PriorYearDepreciationAmt>63</PriorYearDepreciationAmt>
        <ComputationMethodTxt>PRE</ComputationMethodTxt>
        <LifeRt>5.0000</LifeRt>
      </DepreciationPropertyGrp>
      <DepreciationPropertyGrp>
        <PropertyDesc>ANSWERING MACHINE</PropertyDesc>
        <AcquiredDt>1985-12-10</AcquiredDt>
        <CostOrOtherBasisAmt>150</CostOrOtherBasisAmt>
        <PriorYearDepreciationAmt>150</PriorYearDepreciationAmt>
        <ComputationMethodTxt>PRE</ComputationMethodTxt>
        <LifeRt>5.0000</LifeRt>
      </DepreciationPropertyGrp>
      <DepreciationPropertyGrp>
        <PropertyDesc>COPIER</PropertyDesc>
        <AcquiredDt>1986-01-29</AcquiredDt>
        <CostOrOtherBasisAmt>1995</CostOrOtherBasisAmt>
        <PriorYearDepreciationAmt>1995</PriorYearDepreciationAmt>
        <ComputationMethodTxt>PRE</ComputationMethodTxt>
        <LifeRt>5.0000</LifeRt>
      </DepreciationPropertyGrp>
      <DepreciationPropertyGrp>
        <PropertyDesc>RECORDER</PropertyDesc>
        <AcquiredDt>1986-02-12</AcquiredDt>
        <CostOrOtherBasisAmt>27</CostOrOtherBasisAmt>
        <PriorYearDepreciationAmt>27</PriorYearDepreciationAmt>
        <ComputationMethodTxt>PRE</ComputationMethodTxt>
        <LifeRt>5.0000</LifeRt>
      </DepreciationPropertyGrp>
      <DepreciationPropertyGrp>
        <PropertyDesc>TYPEWRITER</PropertyDesc>
        <AcquiredDt>1986-02-12</AcquiredDt>
        <CostOrOtherBasisAmt>323</CostOrOtherBasisAmt>
        <PriorYearDepreciationAmt>323</PriorYearDepreciationAmt>
        <ComputationMethodTxt>PRE</ComputationMethodTxt>
        <LifeRt>5.0000</LifeRt>
      </DepreciationPropertyGrp>
      <DepreciationPropertyGrp>
        <PropertyDesc>SHOP VAC</PropertyDesc>
        <AcquiredDt>1986-04-28</AcquiredDt>
        <CostOrOtherBasisAmt>80</CostOrOtherBasisAmt>
        <PriorYearDepreciationAmt>80</PriorYearDepreciationAmt>
        <ComputationMethodTxt>PRE</ComputationMethodTxt>
        <LifeRt>5.0000</LifeRt>
      </DepreciationPropertyGrp>
      <DepreciationPropertyGrp>
        <PropertyDesc>3 15'FLAG POLES</PropertyDesc>
        <AcquiredDt>1986-10-31</AcquiredDt>
        <CostOrOtherBasisAmt>405</CostOrOtherBasisAmt>
        <PriorYearDepreciationAmt>405</PriorYearDepreciationAmt>
        <ComputationMethodTxt>200DB</ComputationMethodTxt>
        <LifeRt>5.0000</LifeRt>
      </DepreciationPropertyGrp>
      <DepreciationPropertyGrp>
        <PropertyDesc>SECURITY SYSTEMS</PropertyDesc>
        <AcquiredDt>1989-07-01</AcquiredDt>
        <CostOrOtherBasisAmt>530</CostOrOtherBasisAmt>
        <PriorYearDepreciationAmt>530</PriorYearDepreciationAmt>
        <ComputationMethodTxt>200DB</ComputationMethodTxt>
        <LifeRt>7.0000</LifeRt>
      </DepreciationPropertyGrp>
      <DepreciationPropertyGrp>
        <PropertyDesc>TABLE SAW</PropertyDesc>
        <AcquiredDt>1991-07-01</AcquiredDt>
        <CostOrOtherBasisAmt>330</CostOrOtherBasisAmt>
        <PriorYearDepreciationAmt>330</PriorYearDepreciationAmt>
        <ComputationMethodTxt>200DB</ComputationMethodTxt>
        <LifeRt>5.0000</LifeRt>
      </DepreciationPropertyGrp>
      <DepreciationPropertyGrp>
        <PropertyDesc>SLIDE PROJ/CAMERA</PropertyDesc>
        <AcquiredDt>1995-11-13</AcquiredDt>
        <CostOrOtherBasisAmt>480</CostOrOtherBasisAmt>
        <PriorYearDepreciationAmt>480</PriorYearDepreciationAmt>
        <ComputationMethodTxt>S/L</ComputationMethodTxt>
        <LifeRt>5.0000</LifeRt>
      </DepreciationPropertyGrp>
      <DepreciationPropertyGrp>
        <PropertyDesc>FAX MACHINE</PropertyDesc>
        <AcquiredDt>1999-02-06</AcquiredDt>
        <CostOrOtherBasisAmt>115</CostOrOtherBasisAmt>
        <PriorYearDepreciationAmt>115</PriorYearDepreciationAmt>
        <ComputationMethodTxt>200DB</ComputationMethodTxt>
        <LifeRt>5.0000</LifeRt>
      </DepreciationPropertyGrp>
      <DepreciationPropertyGrp>
        <PropertyDesc>PRINTER</PropertyDesc>
        <AcquiredDt>1999-10-27</AcquiredDt>
        <CostOrOtherBasisAmt>163</CostOrOtherBasisAmt>
        <PriorYearDepreciationAmt>163</PriorYearDepreciationAmt>
        <ComputationMethodTxt>200DB</ComputationMethodTxt>
        <LifeRt>5.0000</LifeRt>
      </DepreciationPropertyGrp>
      <DepreciationPropertyGrp>
        <PropertyDesc>CASH REGISTER</PropertyDesc>
        <AcquiredDt>2000-01-14</AcquiredDt>
        <CostOrOtherBasisAmt>120</CostOrOtherBasisAmt>
        <PriorYearDepreciationAmt>120</PriorYearDepreciationAmt>
        <ComputationMethodTxt>200DB</ComputationMethodTxt>
        <LifeRt>7.0000</LifeRt>
      </DepreciationPropertyGrp>
      <DepreciationPropertyGrp>
        <PropertyDesc>BUILDING IMPROVEMENT</PropertyDesc>
        <AcquiredDt>2000-12-31</AcquiredDt>
        <CostOrOtherBasisAmt>9416</CostOrOtherBasisAmt>
        <PriorYearDepreciationAmt>3718</PriorYearDepreciationAmt>
        <ComputationMethodTxt>S/L</ComputationMethodTxt>
        <LifeRt>39.0000</LifeRt>
        <CurrentYearExpenseAmt>235</CurrentYearExpenseAmt>
        <AdjustedNetIncomeAmt>235</AdjustedNetIncomeAmt>
      </DepreciationPropertyGrp>
      <DepreciationPropertyGrp>
        <PropertyDesc>DELL COMPUTER</PropertyDesc>
        <AcquiredDt>2005-03-04</AcquiredDt>
        <CostOrOtherBasisAmt>1033</CostOrOtherBasisAmt>
        <PriorYearDepreciationAmt>1033</PriorYearDepreciationAmt>
        <ComputationMethodTxt>200DB</ComputationMethodTxt>
        <LifeRt>5.0000</LifeRt>
      </DepreciationPropertyGrp>
      <DepreciationPropertyGrp>
        <PropertyDesc>BUILDING IMPROVEMENTS</PropertyDesc>
        <AcquiredDt>2004-12-31</AcquiredDt>
        <CostOrOtherBasisAmt>59649</CostOrOtherBasisAmt>
        <PriorYearDepreciationAmt>18035</PriorYearDepreciationAmt>
        <ComputationMethodTxt>S/L</ComputationMethodTxt>
        <LifeRt>39.0000</LifeRt>
        <CurrentYearExpenseAmt>1529</CurrentYearExpenseAmt>
        <AdjustedNetIncomeAmt>1529</AdjustedNetIncomeAmt>
      </DepreciationPropertyGrp>
      <DepreciationPropertyGrp>
        <PropertyDesc>BUILDING IMPROVEMENTS</PropertyDesc>
        <AcquiredDt>2004-03-31</AcquiredDt>
        <CostOrOtherBasisAmt>21000</CostOrOtherBasisAmt>
        <PriorYearDepreciationAmt>6462</PriorYearDepreciationAmt>
        <ComputationMethodTxt>S/L</ComputationMethodTxt>
        <LifeRt>39.0000</LifeRt>
        <CurrentYearExpenseAmt>538</CurrentYearExpenseAmt>
        <AdjustedNetIncomeAmt>538</AdjustedNetIncomeAmt>
      </DepreciationPropertyGrp>
      <DepreciationPropertyGrp>
        <PropertyDesc>IMPROVEMENTS</PropertyDesc>
        <AcquiredDt>2006-01-07</AcquiredDt>
        <CostOrOtherBasisAmt>978</CostOrOtherBasisAmt>
        <PriorYearDepreciationAmt>269</PriorYearDepreciationAmt>
        <ComputationMethodTxt>S/L</ComputationMethodTxt>
        <LifeRt>39.0000</LifeRt>
        <CurrentYearExpenseAmt>25</CurrentYearExpenseAmt>
        <AdjustedNetIncomeAmt>25</AdjustedNetIncomeAmt>
      </DepreciationPropertyGrp>
      <DepreciationPropertyGrp>
        <PropertyDesc>MUSEUM RENOVATION</PropertyDesc>
        <AcquiredDt>2007-05-05</AcquiredDt>
        <CostOrOtherBasisAmt>987</CostOrOtherBasisAmt>
        <PriorYearDepreciationAmt>237</PriorYearDepreciationAmt>
        <ComputationMethodTxt>S/L</ComputationMethodTxt>
        <LifeRt>39.0000</LifeRt>
        <CurrentYearExpenseAmt>26</CurrentYearExpenseAmt>
        <AdjustedNetIncomeAmt>26</AdjustedNetIncomeAmt>
      </DepreciationPropertyGrp>
      <DepreciationPropertyGrp>
        <PropertyDesc>ENG CONSULTANT SERV</PropertyDesc>
        <AcquiredDt>2011-07-01</AcquiredDt>
        <CostOrOtherBasisAmt>4736</CostOrOtherBasisAmt>
        <PriorYearDepreciationAmt>638</PriorYearDepreciationAmt>
        <ComputationMethodTxt>S/L</ComputationMethodTxt>
        <LifeRt>39.0000</LifeRt>
        <CurrentYearExpenseAmt>121</CurrentYearExpenseAmt>
        <AdjustedNetIncomeAmt>121</AdjustedNetIncomeAmt>
      </DepreciationPropertyGrp>
      <DepreciationPropertyGrp>
        <PropertyDesc>RENOVATION - PHASE II</PropertyDesc>
        <AcquiredDt>2011-07-01</AcquiredDt>
        <CostOrOtherBasisAmt>1318</CostOrOtherBasisAmt>
        <PriorYearDepreciationAmt>177</PriorYearDepreciationAmt>
        <ComputationMethodTxt>S/L</ComputationMethodTxt>
        <LifeRt>39.0000</LifeRt>
        <CurrentYearExpenseAmt>34</CurrentYearExpenseAmt>
        <AdjustedNetIncomeAmt>34</AdjustedNetIncomeAmt>
      </DepreciationPropertyGrp>
      <DepreciationPropertyGrp>
        <PropertyDesc>RENOVATIONS - PHASE II</PropertyDesc>
        <AcquiredDt>2011-12-21</AcquiredDt>
        <CostOrOtherBasisAmt>41868</CostOrOtherBasisAmt>
        <PriorYearDepreciationAmt>5099</PriorYearDepreciationAmt>
        <ComputationMethodTxt>S/L</ComputationMethodTxt>
        <LifeRt>39.0000</LifeRt>
        <CurrentYearExpenseAmt>1074</CurrentYearExpenseAmt>
        <AdjustedNetIncomeAmt>1074</AdjustedNetIncomeAmt>
      </DepreciationPropertyGrp>
      <DepreciationPropertyGrp>
        <PropertyDesc>BULBS</PropertyDesc>
        <AcquiredDt>2012-06-27</AcquiredDt>
        <CostOrOtherBasisAmt>550</CostOrOtherBasisAmt>
        <PriorYearDepreciationAmt>422</PriorYearDepreciationAmt>
        <ComputationMethodTxt>200DB</ComputationMethodTxt>
        <LifeRt>7.0000</LifeRt>
        <CurrentYearExpenseAmt>49</CurrentYearExpenseAmt>
        <AdjustedNetIncomeAmt>49</AdjustedNetIncomeAmt>
      </DepreciationPropertyGrp>
      <DepreciationPropertyGrp>
        <PropertyDesc>DEFIBRILLATOR</PropertyDesc>
        <AcquiredDt>2012-09-28</AcquiredDt>
        <CostOrOtherBasisAmt>1735</CostOrOtherBasisAmt>
        <PriorYearDepreciationAmt>1299</PriorYearDepreciationAmt>
        <ComputationMethodTxt>200DB</ComputationMethodTxt>
        <LifeRt>7.0000</LifeRt>
        <CurrentYearExpenseAmt>152</CurrentYearExpenseAmt>
        <AdjustedNetIncomeAmt>152</AdjustedNetIncomeAmt>
      </DepreciationPropertyGrp>
      <DepreciationPropertyGrp>
        <PropertyDesc>IMPROVEMENTS</PropertyDesc>
        <AcquiredDt>2012-10-31</AcquiredDt>
        <CostOrOtherBasisAmt>3734</CostOrOtherBasisAmt>
        <PriorYearDepreciationAmt>379</PriorYearDepreciationAmt>
        <ComputationMethodTxt>S/L</ComputationMethodTxt>
        <LifeRt>39.0000</LifeRt>
        <CurrentYearExpenseAmt>96</CurrentYearExpenseAmt>
        <AdjustedNetIncomeAmt>96</AdjustedNetIncomeAmt>
      </DepreciationPropertyGrp>
      <DepreciationPropertyGrp>
        <PropertyDesc>IMPROVEMENTS</PropertyDesc>
        <AcquiredDt>2013-01-06</AcquiredDt>
        <CostOrOtherBasisAmt>2599</CostOrOtherBasisAmt>
        <PriorYearDepreciationAmt>247</PriorYearDepreciationAmt>
        <ComputationMethodTxt>S/L</ComputationMethodTxt>
        <LifeRt>39.0000</LifeRt>
        <CurrentYearExpenseAmt>67</CurrentYearExpenseAmt>
        <AdjustedNetIncomeAmt>67</AdjustedNetIncomeAmt>
      </DepreciationPropertyGrp>
      <DepreciationPropertyGrp>
        <PropertyDesc>IMPROVEMENTS</PropertyDesc>
        <AcquiredDt>2013-07-06</AcquiredDt>
        <CostOrOtherBasisAmt>2833</CostOrOtherBasisAmt>
        <PriorYearDepreciationAmt>233</PriorYearDepreciationAmt>
        <ComputationMethodTxt>S/L</ComputationMethodTxt>
        <LifeRt>39.0000</LifeRt>
        <CurrentYearExpenseAmt>73</CurrentYearExpenseAmt>
        <AdjustedNetIncomeAmt>73</AdjustedNetIncomeAmt>
      </DepreciationPropertyGrp>
      <DepreciationPropertyGrp>
        <PropertyDesc>COMPUTER</PropertyDesc>
        <AcquiredDt>2013-10-24</AcquiredDt>
        <CostOrOtherBasisAmt>800</CostOrOtherBasisAmt>
        <PriorYearDepreciationAmt>613</PriorYearDepreciationAmt>
        <ComputationMethodTxt>200DB</ComputationMethodTxt>
        <LifeRt>5.0000</LifeRt>
        <CurrentYearExpenseAmt>88</CurrentYearExpenseAmt>
        <AdjustedNetIncomeAmt>88</AdjustedNetIncomeAmt>
      </DepreciationPropertyGrp>
      <DepreciationPropertyGrp>
        <PropertyDesc>LIGHTING PROJECT</PropertyDesc>
        <AcquiredDt>2013-12-19</AcquiredDt>
        <CostOrOtherBasisAmt>10435</CostOrOtherBasisAmt>
        <PriorYearDepreciationAmt>747</PriorYearDepreciationAmt>
        <ComputationMethodTxt>S/L</ComputationMethodTxt>
        <LifeRt>39.0000</LifeRt>
        <CurrentYearExpenseAmt>268</CurrentYearExpenseAmt>
        <AdjustedNetIncomeAmt>268</AdjustedNetIncomeAmt>
      </DepreciationPropertyGrp>
      <DepreciationPropertyGrp>
        <PropertyDesc>SOUND SYSTEM</PropertyDesc>
        <AcquiredDt>2014-05-21</AcquiredDt>
        <CostOrOtherBasisAmt>1245</CostOrOtherBasisAmt>
        <PriorYearDepreciationAmt>864</PriorYearDepreciationAmt>
        <ComputationMethodTxt>200DB</ComputationMethodTxt>
        <LifeRt>5.0000</LifeRt>
        <CurrentYearExpenseAmt>152</CurrentYearExpenseAmt>
        <AdjustedNetIncomeAmt>152</AdjustedNetIncomeAmt>
      </DepreciationPropertyGrp>
      <DepreciationPropertyGrp>
        <PropertyDesc>SCISSOR LIFT</PropertyDesc>
        <AcquiredDt>2014-09-29</AcquiredDt>
        <CostOrOtherBasisAmt>10850</CostOrOtherBasisAmt>
        <PriorYearDepreciationAmt>5512</PriorYearDepreciationAmt>
        <ComputationMethodTxt>200DB</ComputationMethodTxt>
        <LifeRt>7.0000</LifeRt>
        <CurrentYearExpenseAmt>1525</CurrentYearExpenseAmt>
        <AdjustedNetIncomeAmt>1525</AdjustedNetIncomeAmt>
      </DepreciationPropertyGrp>
      <DepreciationPropertyGrp>
        <PropertyDesc>KISSEL, NASH, AMC CUSTOM BANNERS</PropertyDesc>
        <AcquiredDt>2015-02-13</AcquiredDt>
        <CostOrOtherBasisAmt>2622</CostOrOtherBasisAmt>
        <PriorYearDepreciationAmt>437</PriorYearDepreciationAmt>
        <ComputationMethodTxt>S/L</ComputationMethodTxt>
        <LifeRt>10.0000</LifeRt>
        <CurrentYearExpenseAmt>262</CurrentYearExpenseAmt>
        <AdjustedNetIncomeAmt>262</AdjustedNetIncomeAmt>
      </DepreciationPropertyGrp>
      <DepreciationPropertyGrp>
        <PropertyDesc>CEILING MOUNTED PROJECTOR-SCREEN</PropertyDesc>
        <AcquiredDt>2015-09-30</AcquiredDt>
        <CostOrOtherBasisAmt>1273</CostOrOtherBasisAmt>
        <PriorYearDepreciationAmt>548</PriorYearDepreciationAmt>
        <ComputationMethodTxt>200DB</ComputationMethodTxt>
        <LifeRt>5.0000</LifeRt>
        <CurrentYearExpenseAmt>290</CurrentYearExpenseAmt>
        <AdjustedNetIncomeAmt>290</AdjustedNetIncomeAmt>
      </DepreciationPropertyGrp>
      <DepreciationPropertyGrp>
        <PropertyDesc>STEEL FLAT STORAGE FILES</PropertyDesc>
        <AcquiredDt>2015-09-30</AcquiredDt>
        <CostOrOtherBasisAmt>1174</CostOrOtherBasisAmt>
        <PriorYearDepreciationAmt>365</PriorYearDepreciationAmt>
        <ComputationMethodTxt>200DB</ComputationMethodTxt>
        <LifeRt>7.0000</LifeRt>
        <CurrentYearExpenseAmt>231</CurrentYearExpenseAmt>
        <AdjustedNetIncomeAmt>231</AdjustedNetIncomeAmt>
      </DepreciationPropertyGrp>
      <DepreciationPropertyGrp>
        <PropertyDesc>2ND FLOOR ELECTRICAL WORK</PropertyDesc>
        <AcquiredDt>2016-03-04</AcquiredDt>
        <CostOrOtherBasisAmt>3771</CostOrOtherBasisAmt>
        <PriorYearDepreciationAmt>56</PriorYearDepreciationAmt>
        <ComputationMethodTxt>S/L</ComputationMethodTxt>
        <LifeRt>39.0000</LifeRt>
        <CurrentYearExpenseAmt>97</CurrentYearExpenseAmt>
        <AdjustedNetIncomeAmt>97</AdjustedNetIncomeAmt>
      </DepreciationPropertyGrp>
      <DepreciationPropertyGrp>
        <PropertyDesc>USED FORKLIFT</PropertyDesc>
        <AcquiredDt>2017-09-22</AcquiredDt>
        <CostOrOtherBasisAmt>8000</CostOrOtherBasisAmt>
        <ComputationMethodTxt>200DB</ComputationMethodTxt>
        <LifeRt>7.0000</LifeRt>
        <CurrentYearExpenseAmt>8000</CurrentYearExpenseAmt>
        <AdjustedNetIncomeAmt>8000</AdjustedNetIncomeAmt>
      </DepreciationPropertyGrp>
    </DepreciationSchedule>
    <InvestmentsCorpStockSchedule documentId="RetDoc6">
      <InvestmentsCorporateStockGrp>
        <EOYBookValueAmt>100961</EOYBookValueAmt>
        <EOYFMVAmt>100961</EOYFMVAmt>
      </InvestmentsCorporateStockGrp>
    </InvestmentsCorpStockSchedule>
    <LandEtcSchedule2 documentId="RetDoc7">
      <LandEtcGrp>
        <CategoryOrItemTxt>BUILDINGS</CategoryOrItemTxt>
        <CostOrOtherBasisAmt>900000</CostOrOtherBasisAmt>
        <AccumulatedDepreciationAmt>404063</AccumulatedDepreciationAmt>
        <BookValueAmt>495937</BookValueAmt>
        <EOYFMVAmt>495937</EOYFMVAmt>
      </LandEtcGrp>
      <LandEtcGrp>
        <CategoryOrItemTxt>LEASEHOLD IMPROVEMENTS</CategoryOrItemTxt>
        <CostOrOtherBasisAmt>364298</CostOrOtherBasisAmt>
        <AccumulatedDepreciationAmt>154209</AccumulatedDepreciationAmt>
        <BookValueAmt>210089</BookValueAmt>
        <EOYFMVAmt>210089</EOYFMVAmt>
      </LandEtcGrp>
      <LandEtcGrp>
        <CategoryOrItemTxt>EQUIPMENT</CategoryOrItemTxt>
        <CostOrOtherBasisAmt>30892</CostOrOtherBasisAmt>
        <AccumulatedDepreciationAmt>25453</AccumulatedDepreciationAmt>
        <BookValueAmt>5439</BookValueAmt>
        <EOYFMVAmt>5439</EOYFMVAmt>
      </LandEtcGrp>
      <LandEtcGrp>
        <CategoryOrItemTxt>LAND</CategoryOrItemTxt>
        <CostOrOtherBasisAmt>875</CostOrOtherBasisAmt>
        <BookValueAmt>875</BookValueAmt>
        <EOYFMVAmt>875</EOYFMVAmt>
      </LandEtcGrp>
    </LandEtcSchedule2>
    <OtherAssetsSchedule documentId="RetDoc8">
      <OtherAssetsScheduleGrp>
        <Desc>DONATED VEHICLES</Desc>
        <BOYBookValueAmt>961600</BOYBookValueAmt>
        <EOYBookValueAmt>992100</EOYBookValueAmt>
        <EOYFMVAmt>992100</EOYFMVAmt>
      </OtherAssetsScheduleGrp>
    </OtherAssetsSchedule>
    <OtherExpensesSchedule documentId="RetDoc9">
      <OtherExpensesScheduleGrp>
        <Desc>EXPENSES</Desc>
      </OtherExpensesScheduleGrp>
      <OtherExpensesScheduleGrp>
        <Desc>MISCELLANEOUS</Desc>
        <RevenueAndExpensesPerBooksAmt>1270</RevenueAndExpensesPerBooksAmt>
        <AdjustedNetIncomeAmt>1270</AdjustedNetIncomeAmt>
      </OtherExpensesScheduleGrp>
      <OtherExpensesScheduleGrp>
        <Desc>ADVERTISING</Desc>
        <RevenueAndExpensesPerBooksAmt>3419</RevenueAndExpensesPerBooksAmt>
        <AdjustedNetIncomeAmt>3419</AdjustedNetIncomeAmt>
      </OtherExpensesScheduleGrp>
      <OtherExpensesScheduleGrp>
        <Desc>BANK CHARGES</Desc>
        <RevenueAndExpensesPerBooksAmt>1255</RevenueAndExpensesPerBooksAmt>
        <AdjustedNetIncomeAmt>1255</AdjustedNetIncomeAmt>
      </OtherExpensesScheduleGrp>
      <OtherExpensesScheduleGrp>
        <Desc>DUES &amp; SUBSCRIPTIONS</Desc>
        <RevenueAndExpensesPerBooksAmt>703</RevenueAndExpensesPerBooksAmt>
        <AdjustedNetIncomeAmt>703</AdjustedNetIncomeAmt>
      </OtherExpensesScheduleGrp>
      <OtherExpensesScheduleGrp>
        <Desc>EXHIBIT EXPENSE</Desc>
        <RevenueAndExpensesPerBooksAmt>34</RevenueAndExpensesPerBooksAmt>
        <AdjustedNetIncomeAmt>34</AdjustedNetIncomeAmt>
      </OtherExpensesScheduleGrp>
      <OtherExpensesScheduleGrp>
        <Desc>INSURANCE</Desc>
        <RevenueAndExpensesPerBooksAmt>20485</RevenueAndExpensesPerBooksAmt>
        <NetInvestmentIncomeAmt>2049</NetInvestmentIncomeAmt>
        <AdjustedNetIncomeAmt>18436</AdjustedNetIncomeAmt>
      </OtherExpensesScheduleGrp>
      <OtherExpensesScheduleGrp>
        <Desc>LICENSES &amp; PERMITS</Desc>
        <RevenueAndExpensesPerBooksAmt>205</RevenueAndExpensesPerBooksAmt>
        <AdjustedNetIncomeAmt>205</AdjustedNetIncomeAmt>
      </OtherExpensesScheduleGrp>
      <OtherExpensesScheduleGrp>
        <Desc>OFFICE SUPPLIES</Desc>
        <RevenueAndExpensesPerBooksAmt>563</RevenueAndExpensesPerBooksAmt>
        <AdjustedNetIncomeAmt>563</AdjustedNetIncomeAmt>
      </OtherExpensesScheduleGrp>
      <OtherExpensesScheduleGrp>
        <Desc>PAYROLL SERVICE</Desc>
        <RevenueAndExpensesPerBooksAmt>2370</RevenueAndExpensesPerBooksAmt>
        <AdjustedNetIncomeAmt>2370</AdjustedNetIncomeAmt>
      </OtherExpensesScheduleGrp>
      <OtherExpensesScheduleGrp>
        <Desc>POSTAGE &amp; FREIGHT</Desc>
        <RevenueAndExpensesPerBooksAmt>415</RevenueAndExpensesPerBooksAmt>
        <AdjustedNetIncomeAmt>415</AdjustedNetIncomeAmt>
      </OtherExpensesScheduleGrp>
      <OtherExpensesScheduleGrp>
        <Desc>REPAIRS &amp; MAINTENANCE</Desc>
        <RevenueAndExpensesPerBooksAmt>5376</RevenueAndExpensesPerBooksAmt>
        <AdjustedNetIncomeAmt>5376</AdjustedNetIncomeAmt>
      </OtherExpensesScheduleGrp>
      <OtherExpensesScheduleGrp>
        <Desc>TELEPHONE</Desc>
        <RevenueAndExpensesPerBooksAmt>1315</RevenueAndExpensesPerBooksAmt>
        <AdjustedNetIncomeAmt>1315</AdjustedNetIncomeAmt>
      </OtherExpensesScheduleGrp>
      <OtherExpensesScheduleGrp>
        <Desc>SUPPLIES</Desc>
        <RevenueAndExpensesPerBooksAmt>1116</RevenueAndExpensesPerBooksAmt>
        <AdjustedNetIncomeAmt>1116</AdjustedNetIncomeAmt>
      </OtherExpensesScheduleGrp>
    </OtherExpensesSchedule>
    <OtherIncomeSchedule2 documentId="RetDoc11">
      <OtherIncomeDetail>
        <Desc>ADMISSIONS &amp; TOURS</Desc>
        <RevenueAndExpensesPerBooksAmt>62973</RevenueAndExpensesPerBooksAmt>
        <AdjustedNetIncomeAmt>62973</AdjustedNetIncomeAmt>
      </OtherIncomeDetail>
      <OtherIncomeDetail>
        <Desc>MISCELLANEOUS</Desc>
        <RevenueAndExpensesPerBooksAmt>5425</RevenueAndExpensesPerBooksAmt>
        <AdjustedNetIncomeAmt>5425</AdjustedNetIncomeAmt>
      </OtherIncomeDetail>
    </OtherIncomeSchedule2>
    <OtherIncreasesSchedule documentId="RetDoc10">
      <OtherIncreasesDetail>
        <Desc>INCREASE IN VALUE OF INVESTMENTS</Desc>
        <Amt>777</Amt>
      </OtherIncreasesDetail>
    </OtherIncreasesSchedule>
    <SalesOfInventoryList documentId="RetDoc12">
      <InventorySaleGrp>
        <CategoryTxt>MUSEUM GIFT SHOP</CategoryTxt>
        <GrossSalesAmt>6128</GrossSalesAmt>
        <CostOfGoodsSoldAmt>3003</CostOfGoodsSoldAmt>
        <NetAmt>3125</NetAmt>
      </InventorySaleGrp>
    </SalesOfInventoryList>
    <TaxesSchedule documentId="RetDoc13">
      <TaxesDetail>
        <CategoryTxt>INDIRECT TAXES/LICENSES</CategoryTxt>
        <Amt>1648</Amt>
        <AdjustedNetIncomeAmt>1648</AdjustedNetIncomeAmt>
      </TaxesDetail>
    </TaxesSchedule>
  </ReturnData>
</Return>