<?xml version="1.0" encoding="utf-8"?>
<Return xmlns="http://www.irs.gov/efile" xmlns:xsi="http://www.w3.org/2001/XMLSchema-instance" xsi:schemaLocation="http://www.irs.gov/efile" returnVersion="2017v2.3">
  <ReturnHeader binaryAttachmentCnt="0">
    <ReturnTs>2019-07-03T13:50:17-05:00</ReturnTs>
    <TaxPeriodEndDt>2018-09-30</TaxPeriodEndDt>
    <PreparerFirmGrp>
      <PreparerFirmEIN>363990892</PreparerFirmEIN>
      <PreparerFirmName>
        <BusinessNameLine1Txt>Capin Crouse LLP</BusinessNameLine1Txt>
      </PreparerFirmName>
      <PreparerUSAddress>
        <AddressLine1Txt>2435 Research Parkway Ste 200</AddressLine1Txt>
        <CityNm>Colorado Springs</CityNm>
        <StateAbbreviationCd>CO</StateAbbreviationCd>
        <ZIPCd>80920</ZIPCd>
      </PreparerUSAddress>
    </PreparerFirmGrp>
    <ReturnTypeCd>990</ReturnTypeCd>
    <TaxPeriodBeginDt>2017-10-01</TaxPeriodBeginDt>
    <Filer>
      <EIN>208424918</EIN>
      <BusinessName>
        <BusinessNameLine1Txt>FH Association</BusinessNameLine1Txt>
      </BusinessName>
      <BusinessNameControlTxt>FHAS</BusinessNameControlTxt>
      <PhoneNum>8002486437</PhoneNum>
      <USAddress>
        <AddressLine1Txt>1224 E Washington Street</AddressLine1Txt>
        <CityNm>Phoenix</CityNm>
        <StateAbbreviationCd>AZ</StateAbbreviationCd>
        <ZIPCd>850341102</ZIPCd>
      </USAddress>
    </Filer>
    <BusinessOfficerGrp>
      <PersonNm>Barry Gardner</PersonNm>
      <PersonTitleTxt>CFO</PersonTitleTxt>
      <PhoneNum>8002486437</PhoneNum>
      <SignatureDt>2019-07-03</SignatureDt>
      <DiscussWithPaidPreparerInd>1</DiscussWithPaidPreparerInd>
    </BusinessOfficerGrp>
    <PreparerPersonGrp>
      <PreparerPersonNm>Ted R Batson Jr</PreparerPersonNm>
      <PTIN>P00721951</PTIN>
      <PhoneNum>7195286225</PhoneNum>
    </PreparerPersonGrp>
    <FilingSecurityInformation>
      <IPAddress>
        <IPv4AddressTxt>139.146.132.42</IPv4AddressTxt>
      </IPAddress>
      <IPDt>2019-07-03</IPDt>
      <IPTm>14:50:04</IPTm>
      <IPTimezoneCd>ED</IPTimezoneCd>
      <FilingLicenseTypeCd>P</FilingLicenseTypeCd>
      <AtSubmissionCreationDeviceId>A95F57BE6A7320804B2C667D575C783991090BD8</AtSubmissionCreationDeviceId>
      <AtSubmissionFilingDeviceId>3D7FC1036700EF49DAB888642BD4FE0FA67A9587</AtSubmissionFilingDeviceId>
    </FilingSecurityInformation>
    <TaxYr>2017</TaxYr>
    <BuildTS>2019-02-21 02:37:17Z</BuildTS>
  </ReturnHeader>
  <ReturnData documentCnt="9">
    <IRS990 documentId="RetDoc1038000001" referenceDocumentId="RetDoc1044400001">
      <PrincipalOfficerNm>Gary Edmonds</PrincipalOfficerNm>
      <USAddress>
        <AddressLine1Txt>1224 E Washington Street</AddressLine1Txt>
        <CityNm>Phoenix</CityNm>
        <StateAbbreviationCd>AZ</StateAbbreviationCd>
        <ZIPCd>850341102</ZIPCd>
      </USAddress>
      <GrossReceiptsAmt>103717349</GrossReceiptsAmt>
      <GroupReturnForAffiliatesInd>0</GroupReturnForAffiliatesInd>
      <Organization501cInd organization501cTypeTxt="4">X</Organization501cInd>
      <WebsiteAddressTxt>www.fh.org</WebsiteAddressTxt>
      <TypeOfOrganizationCorpInd>X</TypeOfOrganizationCorpInd>
      <FormationYr>2006</FormationYr>
      <LegalDomicileCountryCd>SZ</LegalDomicileCountryCd>
      <ActivityOrMissionDesc>FH Association is an organization of Christian motivation committed to helping the poor.</ActivityOrMissionDesc>
      <VotingMembersGoverningBodyCnt>9</VotingMembersGoverningBodyCnt>
      <VotingMembersIndependentCnt>9</VotingMembersIndependentCnt>
      <TotalEmployeeCnt>1</TotalEmployeeCnt>
      <TotalVolunteersCnt>22</TotalVolunteersCnt>
      <TotalGrossUBIAmt>0</TotalGrossUBIAmt>
      <NetUnrelatedBusTxblIncmAmt>0</NetUnrelatedBusTxblIncmAmt>
      <PYContributionsGrantsAmt>94280754</PYContributionsGrantsAmt>
      <CYContributionsGrantsAmt>103463897</CYContributionsGrantsAmt>
      <PYProgramServiceRevenueAmt>216759</PYProgramServiceRevenueAmt>
      <CYProgramServiceRevenueAmt>189400</CYProgramServiceRevenueAmt>
      <PYInvestmentIncomeAmt>21005</PYInvestmentIncomeAmt>
      <CYInvestmentIncomeAmt>989</CYInvestmentIncomeAmt>
      <PYOtherRevenueAmt>104938</PYOtherRevenueAmt>
      <CYOtherRevenueAmt>63063</CYOtherRevenueAmt>
      <PYTotalRevenueAmt>94623456</PYTotalRevenueAmt>
      <CYTotalRevenueAmt>103717349</CYTotalRevenueAmt>
      <PYGrantsAndSimilarPaidAmt>29176528</PYGrantsAndSimilarPaidAmt>
      <CYGrantsAndSimilarPaidAmt>25298729</CYGrantsAndSimilarPaidAmt>
      <PYBenefitsPaidToMembersAmt>0</PYBenefitsPaidToMembersAmt>
      <CYBenefitsPaidToMembersAmt>0</CYBenefitsPaidToMembersAmt>
      <PYSalariesCompEmpBnftPaidAmt>19897192</PYSalariesCompEmpBnftPaidAmt>
      <CYSalariesCompEmpBnftPaidAmt>28975060</CYSalariesCompEmpBnftPaidAmt>
      <PYTotalProfFndrsngExpnsAmt>0</PYTotalProfFndrsngExpnsAmt>
      <CYTotalProfFndrsngExpnsAmt>0</CYTotalProfFndrsngExpnsAmt>
      <CYTotalFundraisingExpenseAmt>0</CYTotalFundraisingExpenseAmt>
      <PYOtherExpensesAmt>43355873</PYOtherExpensesAmt>
      <CYOtherExpensesAmt>49102083</CYOtherExpensesAmt>
      <PYTotalExpensesAmt>92429593</PYTotalExpensesAmt>
      <CYTotalExpensesAmt>103375872</CYTotalExpensesAmt>
      <PYRevenuesLessExpensesAmt>2193863</PYRevenuesLessExpensesAmt>
      <CYRevenuesLessExpensesAmt>341477</CYRevenuesLessExpensesAmt>
      <TotalAssetsBOYAmt>17697088</TotalAssetsBOYAmt>
      <TotalAssetsEOYAmt>19670933</TotalAssetsEOYAmt>
      <TotalLiabilitiesBOYAmt>8035240</TotalLiabilitiesBOYAmt>
      <TotalLiabilitiesEOYAmt>9721402</TotalLiabilitiesEOYAmt>
      <NetAssetsOrFundBalancesBOYAmt>9661848</NetAssetsOrFundBalancesBOYAmt>
      <NetAssetsOrFundBalancesEOYAmt>9949531</NetAssetsOrFundBalancesEOYAmt>
      <InfoInScheduleOPartIIIInd>X</InfoInScheduleOPartIIIInd>
      <MissionDesc>FH Association is an organization of Christian motivation committed to helping the poor and needy throughout more than 24 countries in the world by doing disaster/emergency relief and development programs.</MissionDesc>
      <SignificantNewProgramSrvcInd>0</SignificantNewProgramSrvcInd>
      <SignificantChangeInd>0</SignificantChangeInd>
      <ExpenseAmt>40668308</ExpenseAmt>
      <GrantAmt>8239556</GrantAmt>
      <RevenueAmt>112031</RevenueAmt>
      <Desc>Food security and livelihoodSeed fairs, seed and tool distributions, technology enhancement to increase agricultural production, seed multiplication, forestry promotion, soil and water conservation.</Desc>
      <ProgSrvcAccomActy2Grp>
        <ExpenseAmt>26686146</ExpenseAmt>
        <GrantAmt>11069265</GrantAmt>
        <RevenueAmt>19783</RevenueAmt>
        <Desc>HEALTH PROGRAMS-Malnutrition and illness prevention, trainings on proper sanitation practices, health assessments, training and educating of local healthcare representatives, assistance with health insurance provision.HIV/AIDS-Clinical treatment, home-based care, education on proper nutrition and prevention, Biblical training on abstinence and faithfulness, medical support, outreach.</Desc>
      </ProgSrvcAccomActy2Grp>
      <ProgSrvcAccomActy3Grp>
        <ExpenseAmt>17296267</ExpenseAmt>
        <GrantAmt>4246877</GrantAmt>
        <Desc>RELIEF &amp; REHABILITATION PROGRAMS- Emergency relief for droughts, floods and other natural disasters, food distribution, water sanitation activities, health surveys, emergency shelter construction, road and bridge rehabilitation.</Desc>
      </ProgSrvcAccomActy3Grp>
      <ProgSrvcAccomActyOtherGrp>
        <ExpenseAmt>17242007</ExpenseAmt>
        <GrantAmt>1715974</GrantAmt>
        <RevenueAmt>57586</RevenueAmt>
        <Desc>CHILD DEVELOPMENT/EDUCATION &amp; INTEGRATED DEVELOPMENT PROGRAMS- CHILD DEVELOPMENT-Parental counseling, medical checkups, education, school supplies, new skills development, HIV/AIDS awareness trainings, school building rehabilitation.CHILD PROTECTION-Psycho-social care and rehabilitation for traumatized children, advocacy for child-headed households, promotion of children's rights.</Desc>
      </ProgSrvcAccomActyOtherGrp>
      <ProgSrvcAccomActyOtherGrp>
        <ExpenseAmt>1374143</ExpenseAmt>
        <GrantAmt>27058</GrantAmt>
        <Desc>WATER &amp; SANITATION- Irrigation and safe water well construction, hand dug wells, latrine construction, hygiene/sanitation education, water purification, biosand filter for household.</Desc>
      </ProgSrvcAccomActyOtherGrp>
      <ProgSrvcAccomActyOtherGrp>
        <ExpenseAmt>109001</ExpenseAmt>
        <Desc>OTHER PROGRAMS- Church leadership development, leadership training and others.</Desc>
      </ProgSrvcAccomActyOtherGrp>
      <TotalOtherProgSrvcExpenseAmt>18725151</TotalOtherProgSrvcExpenseAmt>
      <TotalOtherProgSrvcGrantAmt>1743032</TotalOtherProgSrvcGrantAmt>
      <TotalOtherProgSrvcRevenueAmt>57586</TotalOtherProgSrvcRevenueAmt>
      <TotalProgramServiceExpensesAmt>103375872</TotalProgramServiceExpensesAmt>
      <DescribedInSection501c3Ind>0</DescribedInSection501c3Ind>
      <ScheduleBRequiredInd referenceDocumentId="RetDoc1234500001">1</ScheduleBRequiredInd>
      <PoliticalCampaignActyInd>0</PoliticalCampaignActyInd>
      <SubjectToProxyTaxInd>0</SubjectToProxyTaxInd>
      <DonorAdvisedFundInd referenceDocumentId="RetDoc1040000001">0</DonorAdvisedFundInd>
      <ConservationEasementsInd referenceDocumentId="RetDoc1040000001">0</ConservationEasementsInd>
      <CollectionsOfArtInd referenceDocumentId="RetDoc1040000001">0</CollectionsOfArtInd>
      <CreditCounselingInd referenceDocumentId="RetDoc1040000001">0</CreditCounselingInd>
      <TempOrPermanentEndowmentsInd referenceDocumentId="RetDoc1040000001">1</TempOrPermanentEndowmentsInd>
      <ReportLandBuildingEquipmentInd referenceDocumentId="RetDoc1040000001">1</ReportLandBuildingEquipmentInd>
      <ReportInvestmentsOtherSecInd referenceDocumentId="RetDoc1040000001">0</ReportInvestmentsOtherSecInd>
      <ReportProgramRelatedInvstInd referenceDocumentId="RetDoc1040000001">0</ReportProgramRelatedInvstInd>
      <ReportOtherAssetsInd referenceDocumentId="RetDoc1040000001">0</ReportOtherAssetsInd>
      <ReportOtherLiabilitiesInd referenceDocumentId="RetDoc1040000001">1</ReportOtherLiabilitiesInd>
      <IncludeFIN48FootnoteInd referenceDocumentId="RetDoc1040000001">0</IncludeFIN48FootnoteInd>
      <IndependentAuditFinclStmtInd referenceDocumentId="RetDoc1040000001">0</IndependentAuditFinclStmtInd>
      <ConsolidatedAuditFinclStmtInd referenceDocumentId="RetDoc1040000001">1</ConsolidatedAuditFinclStmtInd>
      <SchoolOperatingInd>0</SchoolOperatingInd>
      <ForeignOfficeInd>1</ForeignOfficeInd>
      <ForeignActivitiesInd referenceDocumentId="RetDoc1040500001">1</ForeignActivitiesInd>
      <MoreThan5000KToOrgInd referenceDocumentId="RetDoc1040500001">1</MoreThan5000KToOrgInd>
      <MoreThan5000KToIndividualsInd referenceDocumentId="RetDoc1040500001">1</MoreThan5000KToIndividualsInd>
      <ProfessionalFundraisingInd>0</ProfessionalFundraisingInd>
      <FundraisingActivitiesInd>0</FundraisingActivitiesInd>
      <GamingActivitiesInd>0</GamingActivitiesInd>
      <OperateHospitalInd>0</OperateHospitalInd>
      <GrantsToOrganizationsInd referenceDocumentId="RetDoc1041900001">1</GrantsToOrganizationsInd>
      <GrantsToIndividualsInd referenceDocumentId="RetDoc1041900001">0</GrantsToIndividualsInd>
      <ScheduleJRequiredInd referenceDocumentId="RetDoc1042400001">1</ScheduleJRequiredInd>
      <TaxExemptBondsInd>0</TaxExemptBondsInd>
      <EngagedInExcessBenefitTransInd>0</EngagedInExcessBenefitTransInd>
      <PYExcessBenefitTransInd>0</PYExcessBenefitTransInd>
      <LoanOutstandingInd>0</LoanOutstandingInd>
      <GrantToRelatedPersonInd>0</GrantToRelatedPersonInd>
      <BusinessRlnWithOrgMemInd>0</BusinessRlnWithOrgMemInd>
      <BusinessRlnWithFamMemInd>0</BusinessRlnWithFamMemInd>
      <BusinessRlnWithOfficerEntInd>0</BusinessRlnWithOfficerEntInd>
      <DeductibleNonCashContriInd referenceDocumentId="RetDoc1042900001">1</DeductibleNonCashContriInd>
      <DeductibleArtContributionInd referenceDocumentId="RetDoc1042900001">0</DeductibleArtContributionInd>
      <TerminateOperationsInd>0</TerminateOperationsInd>
      <PartialLiquidationInd>0</PartialLiquidationInd>
      <DisregardedEntityInd referenceDocumentId="RetDoc1043400001">0</DisregardedEntityInd>
      <RelatedEntityInd referenceDocumentId="RetDoc1043400001">1</RelatedEntityInd>
      <RelatedOrganizationCtrlEntInd>0</RelatedOrganizationCtrlEntInd>
      <ActivitiesConductedPrtshpInd referenceDocumentId="RetDoc1043400001">0</ActivitiesConductedPrtshpInd>
      <ScheduleORequiredInd>1</ScheduleORequiredInd>
      <InfoInScheduleOPartVInd>X</InfoInScheduleOPartVInd>
      <IRPDocumentCnt>0</IRPDocumentCnt>
      <IRPDocumentW2GCnt>0</IRPDocumentW2GCnt>
      <EmployeeCnt>1</EmployeeCnt>
      <EmploymentTaxReturnsFiledInd>1</EmploymentTaxReturnsFiledInd>
      <UnrelatedBusIncmOverLimitInd>0</UnrelatedBusIncmOverLimitInd>
      <ForeignFinancialAccountInd>1</ForeignFinancialAccountInd>
      <ForeignCountryCd>BY</ForeignCountryCd>
      <ForeignCountryCd>CG</ForeignCountryCd>
      <ForeignCountryCd>ET</ForeignCountryCd>
      <ForeignCountryCd>KE</ForeignCountryCd>
      <ForeignCountryCd>MZ</ForeignCountryCd>
      <ForeignCountryCd>RW</ForeignCountryCd>
      <ForeignCountryCd>OD</ForeignCountryCd>
      <ForeignCountryCd>UG</ForeignCountryCd>
      <ForeignCountryCd>BG</ForeignCountryCd>
      <ForeignCountryCd>CB</ForeignCountryCd>
      <ForeignCountryCd>ID</ForeignCountryCd>
      <ForeignCountryCd>RP</ForeignCountryCd>
      <ForeignCountryCd>BL</ForeignCountryCd>
      <ForeignCountryCd>DR</ForeignCountryCd>
      <ForeignCountryCd>GT</ForeignCountryCd>
      <ForeignCountryCd>HA</ForeignCountryCd>
      <ForeignCountryCd>NU</ForeignCountryCd>
      <ForeignCountryCd>PE</ForeignCountryCd>
      <ProhibitedTaxShelterTransInd>0</ProhibitedTaxShelterTransInd>
      <TaxablePartyNotificationInd>0</TaxablePartyNotificationInd>
      <NondeductibleContributionsInd>0</NondeductibleContributionsInd>
      <IndoorTanningServicesInd>0</IndoorTanningServicesInd>
      <InfoInScheduleOPartVIInd>X</InfoInScheduleOPartVIInd>
      <GoverningBodyVotingMembersCnt>9</GoverningBodyVotingMembersCnt>
      <IndependentVotingMemberCnt>9</IndependentVotingMemberCnt>
      <FamilyOrBusinessRlnInd>0</FamilyOrBusinessRlnInd>
      <DelegationOfMgmtDutiesInd>0</DelegationOfMgmtDutiesInd>
      <ChangeToOrgDocumentsInd>0</ChangeToOrgDocumentsInd>
      <MaterialDiversionOrMisuseInd>0</MaterialDiversionOrMisuseInd>
      <MembersOrStockholdersInd>0</MembersOrStockholdersInd>
      <ElectionOfBoardMembersInd>0</ElectionOfBoardMembersInd>
      <DecisionsSubjectToApprovaInd>0</DecisionsSubjectToApprovaInd>
      <MinutesOfGoverningBodyInd>1</MinutesOfGoverningBodyInd>
      <MinutesOfCommitteesInd>1</MinutesOfCommitteesInd>
      <OfficerMailingAddressInd>0</OfficerMailingAddressInd>
      <LocalChaptersInd>0</LocalChaptersInd>
      <Form990ProvidedToGvrnBodyInd>1</Form990ProvidedToGvrnBodyInd>
      <ConflictOfInterestPolicyInd>1</ConflictOfInterestPolicyInd>
      <AnnualDisclosureCoveredPrsnInd>1</AnnualDisclosureCoveredPrsnInd>
      <RegularMonitoringEnfrcInd>1</RegularMonitoringEnfrcInd>
      <WhistleblowerPolicyInd>1</WhistleblowerPolicyInd>
      <DocumentRetentionPolicyInd>1</DocumentRetentionPolicyInd>
      <CompensationProcessCEOInd>0</CompensationProcessCEOInd>
      <CompensationProcessOtherInd>0</CompensationProcessOtherInd>
      <InvestmentInJointVentureInd>0</InvestmentInJointVentureInd>
      <OwnWebsiteInd>X</OwnWebsiteInd>
      <UponRequestInd>X</UponRequestInd>
      <BooksInCareOfDetail>
        <BusinessName>
          <BusinessNameLine1Txt>Barry Gardner</BusinessNameLine1Txt>
        </BusinessName>
        <PhoneNum>8002486437</PhoneNum>
        <USAddress>
          <AddressLine1Txt>1224 E Washington Street</AddressLine1Txt>
          <CityNm>Phoenix</CityNm>
          <StateAbbreviationCd>AZ</StateAbbreviationCd>
          <ZIPCd>850341102</ZIPCd>
        </USAddress>
      </BooksInCareOfDetail>
      <Form990PartVIISectionAGrp>
        <PersonNm>Larry Jones</PersonNm>
        <TitleTxt>Board Member/Board Co-Chai</TitleTxt>
        <AverageHoursPerWeekRt>0.50</AverageHoursPerWeekRt>
        <AverageHoursPerWeekRltdOrgRt>1.50</AverageHoursPerWeekRltdOrgRt>
        <IndividualTrusteeOrDirectorInd>X</IndividualTrusteeOrDirectorInd>
        <OfficerInd>X</OfficerInd>
        <ReportableCompFromOrgAmt>0</ReportableCompFromOrgAmt>
        <ReportableCompFromRltdOrgAmt>0</ReportableCompFromRltdOrgAmt>
        <OtherCompensationAmt>0</OtherCompensationAmt>
      </Form990PartVIISectionAGrp>
      <Form990PartVIISectionAGrp>
        <PersonNm>Peter Mogan</PersonNm>
        <TitleTxt>Board Vice-Chair</TitleTxt>
        <AverageHoursPerWeekRt>0.50</AverageHoursPerWeekRt>
        <AverageHoursPerWeekRltdOrgRt>1.50</AverageHoursPerWeekRltdOrgRt>
        <IndividualTrusteeOrDirectorInd>X</IndividualTrusteeOrDirectorInd>
        <OfficerInd>X</OfficerInd>
        <ReportableCompFromOrgAmt>0</ReportableCompFromOrgAmt>
        <ReportableCompFromRltdOrgAmt>0</ReportableCompFromRltdOrgAmt>
        <OtherCompensationAmt>0</OtherCompensationAmt>
      </Form990PartVIISectionAGrp>
      <Form990PartVIISectionAGrp>
        <PersonNm>Francoise Andre</PersonNm>
        <TitleTxt>Board Member/Secretary</TitleTxt>
        <AverageHoursPerWeekRt>0.50</AverageHoursPerWeekRt>
        <AverageHoursPerWeekRltdOrgRt>1.50</AverageHoursPerWeekRltdOrgRt>
        <IndividualTrusteeOrDirectorInd>X</IndividualTrusteeOrDirectorInd>
        <OfficerInd>X</OfficerInd>
        <ReportableCompFromOrgAmt>0</ReportableCompFromOrgAmt>
        <ReportableCompFromRltdOrgAmt>0</ReportableCompFromRltdOrgAmt>
        <OtherCompensationAmt>0</OtherCompensationAmt>
      </Form990PartVIISectionAGrp>
      <Form990PartVIISectionAGrp>
        <PersonNm>Jeanie Dassow MD</PersonNm>
        <TitleTxt>Board Member</TitleTxt>
        <AverageHoursPerWeekRt>0.50</AverageHoursPerWeekRt>
        <AverageHoursPerWeekRltdOrgRt>1.50</AverageHoursPerWeekRltdOrgRt>
        <IndividualTrusteeOrDirectorInd>X</IndividualTrusteeOrDirectorInd>
        <ReportableCompFromOrgAmt>0</ReportableCompFromOrgAmt>
        <ReportableCompFromRltdOrgAmt>0</ReportableCompFromRltdOrgAmt>
        <OtherCompensationAmt>0</OtherCompensationAmt>
      </Form990PartVIISectionAGrp>
      <Form990PartVIISectionAGrp>
        <PersonNm>Steven Corbett</PersonNm>
        <TitleTxt>Board Member</TitleTxt>
        <AverageHoursPerWeekRt>0.50</AverageHoursPerWeekRt>
        <AverageHoursPerWeekRltdOrgRt>1.50</AverageHoursPerWeekRltdOrgRt>
        <IndividualTrusteeOrDirectorInd>X</IndividualTrusteeOrDirectorInd>
        <ReportableCompFromOrgAmt>0</ReportableCompFromOrgAmt>
        <ReportableCompFromRltdOrgAmt>0</ReportableCompFromRltdOrgAmt>
        <OtherCompensationAmt>0</OtherCompensationAmt>
      </Form990PartVIISectionAGrp>
      <Form990PartVIISectionAGrp>
        <PersonNm>Paul Graves</PersonNm>
        <TitleTxt>Board Member</TitleTxt>
        <AverageHoursPerWeekRt>0.50</AverageHoursPerWeekRt>
        <AverageHoursPerWeekRltdOrgRt>1.50</AverageHoursPerWeekRltdOrgRt>
        <IndividualTrusteeOrDirectorInd>X</IndividualTrusteeOrDirectorInd>
        <ReportableCompFromOrgAmt>0</ReportableCompFromOrgAmt>
        <ReportableCompFromRltdOrgAmt>0</ReportableCompFromRltdOrgAmt>
        <OtherCompensationAmt>0</OtherCompensationAmt>
      </Form990PartVIISectionAGrp>
      <Form990PartVIISectionAGrp>
        <PersonNm>Me Cir Donnah Kamashazi Gasana</PersonNm>
        <TitleTxt>Board Member</TitleTxt>
        <AverageHoursPerWeekRt>0.50</AverageHoursPerWeekRt>
        <AverageHoursPerWeekRltdOrgRt>1.50</AverageHoursPerWeekRltdOrgRt>
        <IndividualTrusteeOrDirectorInd>X</IndividualTrusteeOrDirectorInd>
        <ReportableCompFromOrgAmt>0</ReportableCompFromOrgAmt>
        <ReportableCompFromRltdOrgAmt>0</ReportableCompFromRltdOrgAmt>
        <OtherCompensationAmt>0</OtherCompensationAmt>
      </Form990PartVIISectionAGrp>
      <Form990PartVIISectionAGrp>
        <PersonNm>Kim Mizuno</PersonNm>
        <TitleTxt>Board Member</TitleTxt>
        <AverageHoursPerWeekRt>0.50</AverageHoursPerWeekRt>
        <AverageHoursPerWeekRltdOrgRt>1.50</AverageHoursPerWeekRltdOrgRt>
        <IndividualTrusteeOrDirectorInd>X</IndividualTrusteeOrDirectorInd>
        <ReportableCompFromOrgAmt>0</ReportableCompFromOrgAmt>
        <ReportableCompFromRltdOrgAmt>0</ReportableCompFromRltdOrgAmt>
        <OtherCompensationAmt>0</OtherCompensationAmt>
      </Form990PartVIISectionAGrp>
      <Form990PartVIISectionAGrp>
        <PersonNm>Alan Holmer</PersonNm>
        <TitleTxt>Board Member</TitleTxt>
        <AverageHoursPerWeekRt>0.50</AverageHoursPerWeekRt>
        <AverageHoursPerWeekRltdOrgRt>1.50</AverageHoursPerWeekRltdOrgRt>
        <IndividualTrusteeOrDirectorInd>X</IndividualTrusteeOrDirectorInd>
        <ReportableCompFromOrgAmt>0</ReportableCompFromOrgAmt>
        <ReportableCompFromRltdOrgAmt>0</ReportableCompFromRltdOrgAmt>
        <OtherCompensationAmt>0</OtherCompensationAmt>
      </Form990PartVIISectionAGrp>
      <Form990PartVIISectionAGrp>
        <PersonNm>Gary Edmonds</PersonNm>
        <TitleTxt>CEO</TitleTxt>
        <AverageHoursPerWeekRt>1.00</AverageHoursPerWeekRt>
        <AverageHoursPerWeekRltdOrgRt>41.00</AverageHoursPerWeekRltdOrgRt>
        <OfficerInd>X</OfficerInd>
        <ReportableCompFromOrgAmt>0</ReportableCompFromOrgAmt>
        <ReportableCompFromRltdOrgAmt>224439</ReportableCompFromRltdOrgAmt>
        <OtherCompensationAmt>24005</OtherCompensationAmt>
      </Form990PartVIISectionAGrp>
      <Form990PartVIISectionAGrp>
        <PersonNm>Barry Gardner</PersonNm>
        <TitleTxt>CFO</TitleTxt>
        <AverageHoursPerWeekRt>1.00</AverageHoursPerWeekRt>
        <AverageHoursPerWeekRltdOrgRt>41.00</AverageHoursPerWeekRltdOrgRt>
        <OfficerInd>X</OfficerInd>
        <ReportableCompFromOrgAmt>0</ReportableCompFromOrgAmt>
        <ReportableCompFromRltdOrgAmt>147600</ReportableCompFromRltdOrgAmt>
        <OtherCompensationAmt>21071</OtherCompensationAmt>
      </Form990PartVIISectionAGrp>
      <TotalReportableCompFromOrgAmt>0</TotalReportableCompFromOrgAmt>
      <TotReportableCompRltdOrgAmt>372039</TotReportableCompRltdOrgAmt>
      <TotalOtherCompensationAmt>45076</TotalOtherCompensationAmt>
      <IndivRcvdGreaterThan100KCnt>0</IndivRcvdGreaterThan100KCnt>
      <FormerOfcrEmployeesListedInd>0</FormerOfcrEmployeesListedInd>
      <TotalCompGreaterThan150KInd>1</TotalCompGreaterThan150KInd>
      <CompensationFromOtherSrcsInd>0</CompensationFromOtherSrcsInd>
      <ContractorCompensationGrp>
        <ContractorName>
          <BusinessName>
            <BusinessNameLine1Txt>Search for Common Ground</BusinessNameLine1Txt>
          </BusinessName>
        </ContractorName>
        <ContractorAddress>
          <USAddress>
            <AddressLine1Txt>1601 Connecticut Ave NW Ste 200</AddressLine1Txt>
            <CityNm>Washington</CityNm>
            <StateAbbreviationCd>DC</StateAbbreviationCd>
            <ZIPCd>20009</ZIPCd>
          </USAddress>
        </ContractorAddress>
        <ServicesDesc>Conflict Resolution</ServicesDesc>
        <CompensationAmt>1490103</CompensationAmt>
      </ContractorCompensationGrp>
      <ContractorCompensationGrp>
        <ContractorName>
          <BusinessName>
            <BusinessNameLine1Txt>International Institute of Tropical Agri</BusinessNameLine1Txt>
          </BusinessName>
        </ContractorName>
        <ContractorAddress>
          <ForeignAddress>
            <AddressLine1Txt>PMB 5320</AddressLine1Txt>
            <CityNm>Ibadan</CityNm>
            <ProvinceOrStateNm>Oyo State</ProvinceOrStateNm>
            <CountryCd>NI</CountryCd>
          </ForeignAddress>
        </ContractorAddress>
        <ServicesDesc>Agricultural</ServicesDesc>
        <CompensationAmt>476166</CompensationAmt>
      </ContractorCompensationGrp>
      <CntrctRcvdGreaterThan100KCnt>2</CntrctRcvdGreaterThan100KCnt>
      <RelatedOrganizationsAmt>37263079</RelatedOrganizationsAmt>
      <GovernmentGrantsAmt>55947733</GovernmentGrantsAmt>
      <AllOtherContributionsAmt>10253085</AllOtherContributionsAmt>
      <NoncashContributionsAmt>21609019</NoncashContributionsAmt>
      <TotalContributionsAmt>103463897</TotalContributionsAmt>
      <ProgramServiceRevenueGrp>
        <Desc>Program Services</Desc>
        <BusinessCd>900099</BusinessCd>
        <TotalRevenueColumnAmt>189400</TotalRevenueColumnAmt>
        <RelatedOrExemptFuncIncomeAmt>189400</RelatedOrExemptFuncIncomeAmt>
      </ProgramServiceRevenueGrp>
      <TotalProgramServiceRevenueAmt>189400</TotalProgramServiceRevenueAmt>
      <InvestmentIncomeGrp>
        <TotalRevenueColumnAmt>989</TotalRevenueColumnAmt>
        <ExclusionAmt>989</ExclusionAmt>
      </InvestmentIncomeGrp>
      <OtherRevenueMiscGrp>
        <Desc>Realized Transl'n Gain</Desc>
        <BusinessCd>900099</BusinessCd>
        <TotalRevenueColumnAmt>63063</TotalRevenueColumnAmt>
        <ExclusionAmt>63063</ExclusionAmt>
      </OtherRevenueMiscGrp>
      <OtherRevenueTotalAmt>63063</OtherRevenueTotalAmt>
      <TotalRevenueGrp>
        <TotalRevenueColumnAmt>103717349</TotalRevenueColumnAmt>
        <RelatedOrExemptFuncIncomeAmt>189400</RelatedOrExemptFuncIncomeAmt>
        <UnrelatedBusinessRevenueAmt>0</UnrelatedBusinessRevenueAmt>
        <ExclusionAmt>64052</ExclusionAmt>
      </TotalRevenueGrp>
      <GrantsToDomesticOrgsGrp>
        <TotalAmt>764994</TotalAmt>
        <ProgramServicesAmt>764994</ProgramServicesAmt>
      </GrantsToDomesticOrgsGrp>
      <ForeignGrantsGrp>
        <TotalAmt>24533735</TotalAmt>
        <ProgramServicesAmt>24533735</ProgramServicesAmt>
      </ForeignGrantsGrp>
      <OtherSalariesAndWagesGrp>
        <TotalAmt>22740300</TotalAmt>
        <ProgramServicesAmt>22740300</ProgramServicesAmt>
      </OtherSalariesAndWagesGrp>
      <PensionPlanContributionsGrp>
        <TotalAmt>1482598</TotalAmt>
        <ProgramServicesAmt>1482598</ProgramServicesAmt>
      </PensionPlanContributionsGrp>
      <OtherEmployeeBenefitsGrp>
        <TotalAmt>4107681</TotalAmt>
        <ProgramServicesAmt>4107681</ProgramServicesAmt>
      </OtherEmployeeBenefitsGrp>
      <PayrollTaxesGrp>
        <TotalAmt>644481</TotalAmt>
        <ProgramServicesAmt>644481</ProgramServicesAmt>
      </PayrollTaxesGrp>
      <FeesForServicesLegalGrp>
        <TotalAmt>164423</TotalAmt>
        <ProgramServicesAmt>164423</ProgramServicesAmt>
      </FeesForServicesLegalGrp>
      <FeesForServicesAccountingGrp>
        <TotalAmt>61658</TotalAmt>
        <ProgramServicesAmt>61658</ProgramServicesAmt>
      </FeesForServicesAccountingGrp>
      <FeesForServicesOtherGrp>
        <TotalAmt>1229486</TotalAmt>
        <ProgramServicesAmt>1229486</ProgramServicesAmt>
      </FeesForServicesOtherGrp>
      <OfficeExpensesGrp>
        <TotalAmt>2389746</TotalAmt>
        <ProgramServicesAmt>2389746</ProgramServicesAmt>
      </OfficeExpensesGrp>
      <OccupancyGrp>
        <TotalAmt>3308900</TotalAmt>
        <ProgramServicesAmt>3308900</ProgramServicesAmt>
      </OccupancyGrp>
      <TravelGrp>
        <TotalAmt>7911790</TotalAmt>
        <ProgramServicesAmt>7911790</ProgramServicesAmt>
      </TravelGrp>
      <ConferencesMeetingsGrp>
        <TotalAmt>805801</TotalAmt>
        <ProgramServicesAmt>805801</ProgramServicesAmt>
      </ConferencesMeetingsGrp>
      <DepreciationDepletionGrp>
        <TotalAmt>1799</TotalAmt>
        <ProgramServicesAmt>1799</ProgramServicesAmt>
      </DepreciationDepletionGrp>
      <OtherExpensesGrp>
        <Desc>Program Materials</Desc>
        <TotalAmt>20894353</TotalAmt>
        <ProgramServicesAmt>20894353</ProgramServicesAmt>
      </OtherExpensesGrp>
      <OtherExpensesGrp>
        <Desc>Transport Expenses</Desc>
        <TotalAmt>10957580</TotalAmt>
        <ProgramServicesAmt>10957580</ProgramServicesAmt>
      </OtherExpensesGrp>
      <OtherExpensesGrp>
        <Desc>Temporary Labor</Desc>
        <TotalAmt>1308360</TotalAmt>
        <ProgramServicesAmt>1308360</ProgramServicesAmt>
      </OtherExpensesGrp>
      <OtherExpensesGrp>
        <Desc>Entertainment/Hospitali</Desc>
        <TotalAmt>20563</TotalAmt>
        <ProgramServicesAmt>20563</ProgramServicesAmt>
      </OtherExpensesGrp>
      <AllOtherExpensesGrp>
        <TotalAmt>47624</TotalAmt>
        <ProgramServicesAmt>47624</ProgramServicesAmt>
      </AllOtherExpensesGrp>
      <TotalFunctionalExpensesGrp>
        <TotalAmt>103375872</TotalAmt>
        <ProgramServicesAmt>103375872</ProgramServicesAmt>
        <ManagementAndGeneralAmt>0</ManagementAndGeneralAmt>
        <FundraisingAmt>0</FundraisingAmt>
      </TotalFunctionalExpensesGrp>
      <CashNonInterestBearingGrp>
        <BOYAmt>13107767</BOYAmt>
        <EOYAmt>7850083</EOYAmt>
      </CashNonInterestBearingGrp>
      <SavingsAndTempCashInvstGrp>
        <BOYAmt>259495</BOYAmt>
        <EOYAmt>420331</EOYAmt>
      </SavingsAndTempCashInvstGrp>
      <PledgesAndGrantsReceivableGrp>
        <BOYAmt>640696</BOYAmt>
        <EOYAmt>1962169</EOYAmt>
      </PledgesAndGrantsReceivableGrp>
      <AccountsReceivableGrp>
        <BOYAmt>965472</BOYAmt>
        <EOYAmt>755703</EOYAmt>
      </AccountsReceivableGrp>
      <OthNotesLoansReceivableNetGrp>
        <BOYAmt>82276</BOYAmt>
        <EOYAmt>4748</EOYAmt>
      </OthNotesLoansReceivableNetGrp>
      <InventoriesForSaleOrUseGrp>
        <BOYAmt>1540068</BOYAmt>
        <EOYAmt>2809525</EOYAmt>
      </InventoriesForSaleOrUseGrp>
      <PrepaidExpensesDefrdChargesGrp>
        <BOYAmt>532029</BOYAmt>
        <EOYAmt>691895</EOYAmt>
      </PrepaidExpensesDefrdChargesGrp>
      <LandBldgEquipCostOrOtherBssAmt>3741645</LandBldgEquipCostOrOtherBssAmt>
      <LandBldgEquipAccumDeprecAmt>3037392</LandBldgEquipAccumDeprecAmt>
      <LandBldgEquipBasisNetGrp>
        <BOYAmt>560878</BOYAmt>
        <EOYAmt>704253</EOYAmt>
      </LandBldgEquipBasisNetGrp>
      <InvestmentsPubTradedSecGrp>
        <BOYAmt>8407</BOYAmt>
        <EOYAmt>4472226</EOYAmt>
      </InvestmentsPubTradedSecGrp>
      <TotalAssetsGrp>
        <BOYAmt>17697088</BOYAmt>
        <EOYAmt>19670933</EOYAmt>
      </TotalAssetsGrp>
      <AccountsPayableAccrExpnssGrp>
        <BOYAmt>4163808</BOYAmt>
        <EOYAmt>4968486</EOYAmt>
      </AccountsPayableAccrExpnssGrp>
      <DeferredRevenueGrp>
        <BOYAmt>2472374</BOYAmt>
        <EOYAmt>2829270</EOYAmt>
      </DeferredRevenueGrp>
      <MortgNotesPyblScrdInvstPropGrp>
        <BOYAmt>157284</BOYAmt>
        <EOYAmt>67834</EOYAmt>
      </MortgNotesPyblScrdInvstPropGrp>
      <OtherLiabilitiesGrp>
        <BOYAmt>1241774</BOYAmt>
        <EOYAmt>1855812</EOYAmt>
      </OtherLiabilitiesGrp>
      <TotalLiabilitiesGrp>
        <BOYAmt>8035240</BOYAmt>
        <EOYAmt>9721402</EOYAmt>
      </TotalLiabilitiesGrp>
      <OrganizationFollowsSFAS117Ind>X</OrganizationFollowsSFAS117Ind>
      <UnrestrictedNetAssetsGrp>
        <BOYAmt>2329574</BOYAmt>
        <EOYAmt>2155219</EOYAmt>
      </UnrestrictedNetAssetsGrp>
      <TemporarilyRstrNetAssetsGrp>
        <BOYAmt>7332274</BOYAmt>
        <EOYAmt>7794312</EOYAmt>
      </TemporarilyRstrNetAssetsGrp>
      <TotalNetAssetsFundBalanceGrp>
        <BOYAmt>9661848</BOYAmt>
        <EOYAmt>9949531</EOYAmt>
      </TotalNetAssetsFundBalanceGrp>
      <TotLiabNetAssetsFundBalanceGrp>
        <BOYAmt>17697088</BOYAmt>
        <EOYAmt>19670933</EOYAmt>
      </TotLiabNetAssetsFundBalanceGrp>
      <InfoInScheduleOPartXIInd>X</InfoInScheduleOPartXIInd>
      <ReconcilationRevenueExpnssAmt>341477</ReconcilationRevenueExpnssAmt>
      <OtherChangesInNetAssetsAmt>-53794</OtherChangesInNetAssetsAmt>
      <InfoInScheduleOPartXIIInd>X</InfoInScheduleOPartXIIInd>
      <MethodOfAccountingAccrualInd>X</MethodOfAccountingAccrualInd>
      <AccountantCompileOrReviewInd>0</AccountantCompileOrReviewInd>
      <FSAuditedInd>1</FSAuditedInd>
      <FSAuditedBasisGrp>
        <ConsolidatedBasisFinclStmtInd>X</ConsolidatedBasisFinclStmtInd>
      </FSAuditedBasisGrp>
      <AuditCommitteeInd>1</AuditCommitteeInd>
      <FederalGrantAuditRequiredInd>1</FederalGrantAuditRequiredInd>
      <FederalGrantAuditPerformedInd>1</FederalGrantAuditPerformedInd>
    </IRS990>
    <IRS990ScheduleB documentId="RetDoc1234500001" />
    <IRS990ScheduleD documentId="RetDoc1040000001">
      <CYEndwmtFundGrp>
        <BeginningYearBalanceAmt>1255248</BeginningYearBalanceAmt>
        <InvestmentEarningsOrLossesAmt>187603</InvestmentEarningsOrLossesAmt>
        <GrantsOrScholarshipsAmt>66840</GrantsOrScholarshipsAmt>
        <EndYearBalanceAmt>1376011</EndYearBalanceAmt>
      </CYEndwmtFundGrp>
      <CYMinus1YrEndwmtFundGrp>
        <BeginningYearBalanceAmt>1150827</BeginningYearBalanceAmt>
        <InvestmentEarningsOrLossesAmt>163621</InvestmentEarningsOrLossesAmt>
        <GrantsOrScholarshipsAmt>59200</GrantsOrScholarshipsAmt>
        <EndYearBalanceAmt>1255248</EndYearBalanceAmt>
      </CYMinus1YrEndwmtFundGrp>
      <CYMinus2YrEndwmtFundGrp>
        <BeginningYearBalanceAmt>1082394</BeginningYearBalanceAmt>
        <InvestmentEarningsOrLossesAmt>123057</InvestmentEarningsOrLossesAmt>
        <GrantsOrScholarshipsAmt>54624</GrantsOrScholarshipsAmt>
        <EndYearBalanceAmt>1150827</EndYearBalanceAmt>
      </CYMinus2YrEndwmtFundGrp>
      <CYMinus3YrEndwmtFundGrp>
        <BeginningYearBalanceAmt>1144527</BeginningYearBalanceAmt>
        <InvestmentEarningsOrLossesAmt>-1509</InvestmentEarningsOrLossesAmt>
        <GrantsOrScholarshipsAmt>60624</GrantsOrScholarshipsAmt>
        <EndYearBalanceAmt>1082394</EndYearBalanceAmt>
      </CYMinus3YrEndwmtFundGrp>
      <CYMinus4YrEndwmtFundGrp>
        <BeginningYearBalanceAmt>1063162</BeginningYearBalanceAmt>
        <InvestmentEarningsOrLossesAmt>136865</InvestmentEarningsOrLossesAmt>
        <GrantsOrScholarshipsAmt>55500</GrantsOrScholarshipsAmt>
        <EndYearBalanceAmt>1144527</EndYearBalanceAmt>
      </CYMinus4YrEndwmtFundGrp>
      <PrmnntEndowmentBalanceEOYPct>0.36340</PrmnntEndowmentBalanceEOYPct>
      <TermEndowmentBalanceEOYPct>0.63660</TermEndowmentBalanceEOYPct>
      <EndowmentsHeldUnrelatedOrgInd>0</EndowmentsHeldUnrelatedOrgInd>
      <EndowmentsHeldRelatedOrgInd>1</EndowmentsHeldRelatedOrgInd>
      <RelatedOrgListSchRInd>1</RelatedOrgListSchRInd>
      <EquipmentGrp>
        <OtherCostOrOtherBasisAmt>237482</OtherCostOrOtherBasisAmt>
        <DepreciationAmt>237482</DepreciationAmt>
        <BookValueAmt>0</BookValueAmt>
      </EquipmentGrp>
      <OtherLandBuildingsGrp>
        <OtherCostOrOtherBasisAmt>3504163</OtherCostOrOtherBasisAmt>
        <DepreciationAmt>2799910</DepreciationAmt>
        <BookValueAmt>704253</BookValueAmt>
      </OtherLandBuildingsGrp>
      <TotalBookValueLandBuildingsAmt>704253</TotalBookValueLandBuildingsAmt>
      <OtherLiabilitiesOrgGrp>
        <Desc>Pension liability</Desc>
        <Amt>1810033</Amt>
      </OtherLiabilitiesOrgGrp>
      <OtherLiabilitiesOrgGrp>
        <Desc>Refundable advances</Desc>
        <Amt>45779</Amt>
      </OtherLiabilitiesOrgGrp>
      <TotalLiabilityAmt>1855812</TotalLiabilityAmt>
      <SupplementalInformationDetail>
        <FormAndLineReferenceDesc>Part V, Line 4:</FormAndLineReferenceDesc>
        <ExplanationTxt>The primary purpose of the organization's endowment funds is to provide child development program students with vocational training or secondary schooling scholarship assistance. The vision is for them to complete a degree of education that will adequately allow them to develop their capacities and prepare them to fulfill their role and purpose in their family and community, finishing with the tools they need to live a good life.</ExplanationTxt>
      </SupplementalInformationDetail>
    </IRS990ScheduleD>
    <IRS990ScheduleF documentId="RetDoc1040500001">
      <GrantRecordsMaintainedInd>1</GrantRecordsMaintainedInd>
      <AccountActivitiesOutsideUSGrp>
        <RegionTxt>Central America and the Caribbean</RegionTxt>
        <OfficesCnt>5</OfficesCnt>
        <EmployeeCnt>390</EmployeeCnt>
        <TypeOfActivitiesConductedTxt>Program Services</TypeOfActivitiesConductedTxt>
        <SpecificServicesProvidedTxt>Relief &amp; Development</SpecificServicesProvidedTxt>
        <RegionTotalExpendituresAmt>7810692</RegionTotalExpendituresAmt>
      </AccountActivitiesOutsideUSGrp>
      <AccountActivitiesOutsideUSGrp>
        <RegionTxt>Central America and the Caribbean</RegionTxt>
        <OfficesCnt>0</OfficesCnt>
        <EmployeeCnt>0</EmployeeCnt>
        <TypeOfActivitiesConductedTxt>Grants to Recipients Located in Region</TypeOfActivitiesConductedTxt>
        <RegionTotalExpendituresAmt>960431</RegionTotalExpendituresAmt>
      </AccountActivitiesOutsideUSGrp>
      <AccountActivitiesOutsideUSGrp>
        <RegionTxt>East Asia and the Pacific</RegionTxt>
        <OfficesCnt>4</OfficesCnt>
        <EmployeeCnt>343</EmployeeCnt>
        <TypeOfActivitiesConductedTxt>Program Services</TypeOfActivitiesConductedTxt>
        <SpecificServicesProvidedTxt>Relief &amp; Development</SpecificServicesProvidedTxt>
        <RegionTotalExpendituresAmt>4321982</RegionTotalExpendituresAmt>
      </AccountActivitiesOutsideUSGrp>
      <AccountActivitiesOutsideUSGrp>
        <RegionTxt>East Asia and the Pacific</RegionTxt>
        <OfficesCnt>0</OfficesCnt>
        <EmployeeCnt>0</EmployeeCnt>
        <TypeOfActivitiesConductedTxt>Grants to Recipients Located in Region</TypeOfActivitiesConductedTxt>
        <RegionTotalExpendituresAmt>53812</RegionTotalExpendituresAmt>
      </AccountActivitiesOutsideUSGrp>
      <AccountActivitiesOutsideUSGrp>
        <RegionTxt>South America</RegionTxt>
        <OfficesCnt>2</OfficesCnt>
        <EmployeeCnt>191</EmployeeCnt>
        <TypeOfActivitiesConductedTxt>Program Services</TypeOfActivitiesConductedTxt>
        <SpecificServicesProvidedTxt>Relief &amp; Development</SpecificServicesProvidedTxt>
        <RegionTotalExpendituresAmt>4036358</RegionTotalExpendituresAmt>
      </AccountActivitiesOutsideUSGrp>
      <AccountActivitiesOutsideUSGrp>
        <RegionTxt>South America</RegionTxt>
        <OfficesCnt>0</OfficesCnt>
        <EmployeeCnt>0</EmployeeCnt>
        <TypeOfActivitiesConductedTxt>Grants to Recipients Located in Region</TypeOfActivitiesConductedTxt>
        <RegionTotalExpendituresAmt>6317560</RegionTotalExpendituresAmt>
      </AccountActivitiesOutsideUSGrp>
      <AccountActivitiesOutsideUSGrp>
        <RegionTxt>South Asia</RegionTxt>
        <OfficesCnt>1</OfficesCnt>
        <EmployeeCnt>322</EmployeeCnt>
        <TypeOfActivitiesConductedTxt>Program Services</TypeOfActivitiesConductedTxt>
        <SpecificServicesProvidedTxt>Relief &amp; Development</SpecificServicesProvidedTxt>
        <RegionTotalExpendituresAmt>3965590</RegionTotalExpendituresAmt>
      </AccountActivitiesOutsideUSGrp>
      <AccountActivitiesOutsideUSGrp>
        <RegionTxt>South Asia</RegionTxt>
        <OfficesCnt>0</OfficesCnt>
        <EmployeeCnt>0</EmployeeCnt>
        <TypeOfActivitiesConductedTxt>Grants to Recipients Located in Region</TypeOfActivitiesConductedTxt>
        <RegionTotalExpendituresAmt>56888</RegionTotalExpendituresAmt>
      </AccountActivitiesOutsideUSGrp>
      <AccountActivitiesOutsideUSGrp>
        <RegionTxt>Sub-Saharan Africa</RegionTxt>
        <OfficesCnt>8</OfficesCnt>
        <EmployeeCnt>1865</EmployeeCnt>
        <TypeOfActivitiesConductedTxt>Program Services</TypeOfActivitiesConductedTxt>
        <SpecificServicesProvidedTxt>Relief &amp; Development</SpecificServicesProvidedTxt>
        <RegionTotalExpendituresAmt>58707514</RegionTotalExpendituresAmt>
      </AccountActivitiesOutsideUSGrp>
      <AccountActivitiesOutsideUSGrp>
        <RegionTxt>Sub-Saharan Africa</RegionTxt>
        <OfficesCnt>0</OfficesCnt>
        <EmployeeCnt>0</EmployeeCnt>
        <TypeOfActivitiesConductedTxt>Grants to Recipients Located in Region</TypeOfActivitiesConductedTxt>
        <RegionTotalExpendituresAmt>17145044</RegionTotalExpendituresAmt>
      </AccountActivitiesOutsideUSGrp>
      <SubtotalOfficesCnt>12</SubtotalOfficesCnt>
      <SubtotalEmployeesCnt>1246</SubtotalEmployeesCnt>
      <ContinuationTotalOfficeCnt>8</ContinuationTotalOfficeCnt>
      <ContinuationTotalEmployeeCnt>1865</ContinuationTotalEmployeeCnt>
      <TotalOfficeCnt>20</TotalOfficeCnt>
      <TotalEmployeeCnt>3111</TotalEmployeeCnt>
      <SubtotalSpentAmt>27523313</SubtotalSpentAmt>
      <ContinuationSpentAmt>75852558</ContinuationSpentAmt>
      <TotalSpentAmt>103375871</TotalSpentAmt>
      <GrantsToOrgOutsideUSGrp>
        <RegionTxt>Sub-Saharan Africa</RegionTxt>
        <PurposeOfGrantTxt>Strengthening Community Resilience in Marsabit</PurposeOfGrantTxt>
        <CashGrantAmt>63393</CashGrantAmt>
        <MannerOfCashDisbursementTxt>Bank transfer</MannerOfCashDisbursementTxt>
      </GrantsToOrgOutsideUSGrp>
      <GrantsToOrgOutsideUSGrp>
        <RegionTxt>Sub-Saharan Africa</RegionTxt>
        <PurposeOfGrantTxt>Strengthening Community Resilience in Marsabit</PurposeOfGrantTxt>
        <CashGrantAmt>51028</CashGrantAmt>
        <MannerOfCashDisbursementTxt>Bank transfer</MannerOfCashDisbursementTxt>
      </GrantsToOrgOutsideUSGrp>
      <GrantsToOrgOutsideUSGrp>
        <RegionTxt>Sub-Saharan Africa</RegionTxt>
        <PurposeOfGrantTxt>Conflict resolution</PurposeOfGrantTxt>
        <CashGrantAmt>32497</CashGrantAmt>
        <MannerOfCashDisbursementTxt>Bank transfer</MannerOfCashDisbursementTxt>
      </GrantsToOrgOutsideUSGrp>
      <GrantsToOrgOutsideUSGrp>
        <RegionTxt>Sub-Saharan Africa</RegionTxt>
        <PurposeOfGrantTxt>Trainings for intervention, evaluation and laboratory team</PurposeOfGrantTxt>
        <CashGrantAmt>508580</CashGrantAmt>
        <MannerOfCashDisbursementTxt>Bank transfer</MannerOfCashDisbursementTxt>
      </GrantsToOrgOutsideUSGrp>
      <GrantsToOrgOutsideUSGrp>
        <RegionTxt>Sub-Saharan Africa</RegionTxt>
        <PurposeOfGrantTxt>Best farming practices, Agroforestry, Animal health</PurposeOfGrantTxt>
        <CashGrantAmt>476166</CashGrantAmt>
        <MannerOfCashDisbursementTxt>Bank transfer</MannerOfCashDisbursementTxt>
      </GrantsToOrgOutsideUSGrp>
      <GrantsToOrgOutsideUSGrp>
        <RegionTxt>Sub-Saharan Africa</RegionTxt>
        <PurposeOfGrantTxt>Literacy and numeracy training</PurposeOfGrantTxt>
        <CashGrantAmt>50025</CashGrantAmt>
        <MannerOfCashDisbursementTxt>Bank transfer</MannerOfCashDisbursementTxt>
      </GrantsToOrgOutsideUSGrp>
      <GrantsToOrgOutsideUSGrp>
        <RegionTxt>Sub-Saharan Africa</RegionTxt>
        <PurposeOfGrantTxt>Conflict resolution and peace building</PurposeOfGrantTxt>
        <CashGrantAmt>50000</CashGrantAmt>
        <MannerOfCashDisbursementTxt>Bank transfer</MannerOfCashDisbursementTxt>
      </GrantsToOrgOutsideUSGrp>
      <GrantsToOrgOutsideUSGrp>
        <RegionTxt>Sub-Saharan Africa</RegionTxt>
        <PurposeOfGrantTxt>Rehabilitation of school infrastructure and teachers incentive</PurposeOfGrantTxt>
        <CashGrantAmt>80601</CashGrantAmt>
        <MannerOfCashDisbursementTxt>Bank transfer</MannerOfCashDisbursementTxt>
      </GrantsToOrgOutsideUSGrp>
      <GrantsToOrgOutsideUSGrp>
        <RegionTxt>Sub-Saharan Africa</RegionTxt>
        <PurposeOfGrantTxt>Rehabilitation of school infrastructure and teachers incentive</PurposeOfGrantTxt>
        <CashGrantAmt>55125</CashGrantAmt>
        <MannerOfCashDisbursementTxt>Bank transfer</MannerOfCashDisbursementTxt>
      </GrantsToOrgOutsideUSGrp>
      <Total501c3OrgCnt>9</Total501c3OrgCnt>
      <TotalOtherOrgCnt>0</TotalOtherOrgCnt>
      <ForeignIndividualsGrantsGrp>
        <TypeOfAssistanceTxt>Relief and Development</TypeOfAssistanceTxt>
        <RegionTxt>Central America &amp; the Caribbean</RegionTxt>
        <RecipientCnt>225418</RecipientCnt>
        <MannerOfCashDisbursementTxt>Bank wire transfers and cash given to beneficiaries</MannerOfCashDisbursementTxt>
        <NonCashAssistanceAmt>956129</NonCashAssistanceAmt>
        <DescriptionOfNonCashAsstTxt>Various commodities including but not limited to food and medical supplies</DescriptionOfNonCashAsstTxt>
        <ValuationMethodUsedDesc>Market Value</ValuationMethodUsedDesc>
      </ForeignIndividualsGrantsGrp>
      <ForeignIndividualsGrantsGrp>
        <TypeOfAssistanceTxt>Relief and Development</TypeOfAssistanceTxt>
        <RegionTxt>East Asia and the Pacific</RegionTxt>
        <RecipientCnt>1875</RecipientCnt>
        <MannerOfCashDisbursementTxt>Bank wire transfers and cash given to beneficiaries</MannerOfCashDisbursementTxt>
        <NonCashAssistanceAmt>24326</NonCashAssistanceAmt>
        <DescriptionOfNonCashAsstTxt>Various commodities including but not limited to food and medical supplies</DescriptionOfNonCashAsstTxt>
        <ValuationMethodUsedDesc>Market Value</ValuationMethodUsedDesc>
      </ForeignIndividualsGrantsGrp>
      <ForeignIndividualsGrantsGrp>
        <TypeOfAssistanceTxt>Relief and Development</TypeOfAssistanceTxt>
        <RegionTxt>South Asia</RegionTxt>
        <RecipientCnt>337828</RecipientCnt>
        <MannerOfCashDisbursementTxt>Bank wire transfers and cash given to beneficiaries</MannerOfCashDisbursementTxt>
        <NonCashAssistanceAmt>56888</NonCashAssistanceAmt>
        <DescriptionOfNonCashAsstTxt>Various commodities including but not limited to food and medical supplies</DescriptionOfNonCashAsstTxt>
        <ValuationMethodUsedDesc>Market Value</ValuationMethodUsedDesc>
      </ForeignIndividualsGrantsGrp>
      <ForeignIndividualsGrantsGrp>
        <TypeOfAssistanceTxt>Relief and Development</TypeOfAssistanceTxt>
        <RegionTxt>South America</RegionTxt>
        <RecipientCnt>3018070</RecipientCnt>
        <MannerOfCashDisbursementTxt>Bank wire transfers and cash given to beneficiaries</MannerOfCashDisbursementTxt>
        <NonCashAssistanceAmt>6317560</NonCashAssistanceAmt>
        <DescriptionOfNonCashAsstTxt>Various commodities including but not limited to food and medical supplies</DescriptionOfNonCashAsstTxt>
        <ValuationMethodUsedDesc>Market Value</ValuationMethodUsedDesc>
      </ForeignIndividualsGrantsGrp>
      <ForeignIndividualsGrantsGrp>
        <TypeOfAssistanceTxt>Relief and Development</TypeOfAssistanceTxt>
        <RegionTxt>Sub-Saharan Africa</RegionTxt>
        <RecipientCnt>5287918</RecipientCnt>
        <MannerOfCashDisbursementTxt>Bank wire transfers and cash given to beneficiaries</MannerOfCashDisbursementTxt>
        <NonCashAssistanceAmt>14195719</NonCashAssistanceAmt>
        <DescriptionOfNonCashAsstTxt>Various commodities including but not limited to food and medical supplies</DescriptionOfNonCashAsstTxt>
        <ValuationMethodUsedDesc>Market Value</ValuationMethodUsedDesc>
      </ForeignIndividualsGrantsGrp>
      <TransferToForeignCorpInd>0</TransferToForeignCorpInd>
      <InterestInForeignTrustInd>0</InterestInForeignTrustInd>
      <ForeignCorpOwnershipInd>0</ForeignCorpOwnershipInd>
      <PassiveForeignInvestmestCoInd>0</PassiveForeignInvestmestCoInd>
      <ForeignPartnershipInd>0</ForeignPartnershipInd>
      <BoycottCountriesInd>0</BoycottCountriesInd>
      <SupplementalInformationDetail>
        <FormAndLineReferenceDesc>Part I, Line 2:</FormAndLineReferenceDesc>
        <ExplanationTxt>FH Association monitors program services through regional offices in Asia, Africa and Latin America and each field's headquarters office. The fields and regional offices submit a monthly financial report to the International headquarters office and all financial records are stored in its central server. We also have monitoring and evaluation personnel who visit projects.</ExplanationTxt>
      </SupplementalInformationDetail>
      <SupplementalInformationDetail>
        <FormAndLineReferenceDesc>Part I, line 3:</FormAndLineReferenceDesc>
        <ExplanationTxt>Expenses are accounted for according to the accrual basis of accounting using grant feedback, expense reports, and other appropriate documentation.</ExplanationTxt>
      </SupplementalInformationDetail>
    </IRS990ScheduleF>
    <IRS990ScheduleI documentId="RetDoc1041900001">
      <GrantRecordsMaintainedInd>1</GrantRecordsMaintainedInd>
      <RecipientTable>
        <RecipientBusinessName>
          <BusinessNameLine1Txt>Food for the Hungry Inc</BusinessNameLine1Txt>
        </RecipientBusinessName>
        <USAddress>
          <AddressLine1Txt>1224 E Washington St</AddressLine1Txt>
          <CityNm>Phoenix</CityNm>
          <StateAbbreviationCd>AZ</StateAbbreviationCd>
          <ZIPCd>85034</ZIPCd>
        </USAddress>
        <RecipientEIN>952680390</RecipientEIN>
        <IRCSectionDesc>501(c)(3)</IRCSectionDesc>
        <CashGrantAmt>764994</CashGrantAmt>
        <PurposeOfGrantTxt>Support operations</PurposeOfGrantTxt>
      </RecipientTable>
      <Total501c3OrgCnt>1</Total501c3OrgCnt>
      <TotalOtherOrgCnt>0</TotalOtherOrgCnt>
      <SupplementalInformationDetail>
        <FormAndLineReferenceDesc>Part I, Line 2:</FormAndLineReferenceDesc>
        <ExplanationTxt>FH Association grants funds to Food for the Hungry, Inc., a related organization. The use of funds are monitored by common management.</ExplanationTxt>
      </SupplementalInformationDetail>
    </IRS990ScheduleI>
    <IRS990ScheduleJ documentId="RetDoc1042400001">
      <SeverancePaymentInd>0</SeverancePaymentInd>
      <SupplementalNonqualRtrPlanInd>0</SupplementalNonqualRtrPlanInd>
      <EquityBasedCompArrngmInd>0</EquityBasedCompArrngmInd>
      <CompBasedOnRevenueOfFlngOrgInd>0</CompBasedOnRevenueOfFlngOrgInd>
      <CompBsdOnRevRelatedOrgsInd>0</CompBsdOnRevRelatedOrgsInd>
      <CompBsdNetEarnsFlngOrgInd>0</CompBsdNetEarnsFlngOrgInd>
      <CompBsdNetEarnsRltdOrgsInd>0</CompBsdNetEarnsRltdOrgsInd>
      <AnyNonFixedPaymentsInd>0</AnyNonFixedPaymentsInd>
      <InitialContractExceptionInd>0</InitialContractExceptionInd>
      <RltdOrgOfficerTrstKeyEmplGrp>
        <PersonNm>Gary Edmonds</PersonNm>
        <TitleTxt>CEO</TitleTxt>
        <BaseCompensationFilingOrgAmt>0</BaseCompensationFilingOrgAmt>
        <CompensationBasedOnRltdOrgsAmt>220629</CompensationBasedOnRltdOrgsAmt>
        <BonusFilingOrganizationAmount>0</BonusFilingOrganizationAmount>
        <BonusRelatedOrganizationsAmt>0</BonusRelatedOrganizationsAmt>
        <OtherCompensationFilingOrgAmt>0</OtherCompensationFilingOrgAmt>
        <OtherCompensationRltdOrgsAmt>3810</OtherCompensationRltdOrgsAmt>
        <DeferredCompensationFlngOrgAmt>0</DeferredCompensationFlngOrgAmt>
        <DeferredCompRltdOrgsAmt>8941</DeferredCompRltdOrgsAmt>
        <NontaxableBenefitsFilingOrgAmt>0</NontaxableBenefitsFilingOrgAmt>
        <NontaxableBenefitsRltdOrgsAmt>17133</NontaxableBenefitsRltdOrgsAmt>
        <TotalCompensationFilingOrgAmt>0</TotalCompensationFilingOrgAmt>
        <TotalCompensationRltdOrgsAmt>250513</TotalCompensationRltdOrgsAmt>
        <CompReportPrior990FilingOrgAmt>0</CompReportPrior990FilingOrgAmt>
        <CompReportPrior990RltdOrgsAmt>0</CompReportPrior990RltdOrgsAmt>
      </RltdOrgOfficerTrstKeyEmplGrp>
      <RltdOrgOfficerTrstKeyEmplGrp>
        <PersonNm>Barry Gardner</PersonNm>
        <TitleTxt>CFO</TitleTxt>
        <BaseCompensationFilingOrgAmt>0</BaseCompensationFilingOrgAmt>
        <CompensationBasedOnRltdOrgsAmt>143949</CompensationBasedOnRltdOrgsAmt>
        <BonusFilingOrganizationAmount>0</BonusFilingOrganizationAmount>
        <BonusRelatedOrganizationsAmt>0</BonusRelatedOrganizationsAmt>
        <OtherCompensationFilingOrgAmt>0</OtherCompensationFilingOrgAmt>
        <OtherCompensationRltdOrgsAmt>3651</OtherCompensationRltdOrgsAmt>
        <DeferredCompensationFlngOrgAmt>0</DeferredCompensationFlngOrgAmt>
        <DeferredCompRltdOrgsAmt>6008</DeferredCompRltdOrgsAmt>
        <NontaxableBenefitsFilingOrgAmt>0</NontaxableBenefitsFilingOrgAmt>
        <NontaxableBenefitsRltdOrgsAmt>17133</NontaxableBenefitsRltdOrgsAmt>
        <TotalCompensationFilingOrgAmt>0</TotalCompensationFilingOrgAmt>
        <TotalCompensationRltdOrgsAmt>170741</TotalCompensationRltdOrgsAmt>
        <CompReportPrior990FilingOrgAmt>0</CompReportPrior990FilingOrgAmt>
        <CompReportPrior990RltdOrgsAmt>0</CompReportPrior990RltdOrgsAmt>
      </RltdOrgOfficerTrstKeyEmplGrp>
      <SupplementalInformationDetail>
        <FormAndLineReferenceDesc>Schedule J, Part II:</FormAndLineReferenceDesc>
        <ExplanationTxt>FH Association's U.S. affiliate, Food for the Hungry, Inc., determines officer compensation by looking at the 990s of other organizations and by reviewing compensation surveys. The final recommendation is approved by the Board of Directors.</ExplanationTxt>
      </SupplementalInformationDetail>
    </IRS990ScheduleJ>
    <IRS990ScheduleM documentId="RetDoc1042900001">
      <FoodInventoryGrp>
        <NonCashCheckboxInd>X</NonCashCheckboxInd>
        <ContributionCnt>52</ContributionCnt>
        <NoncashContributionsRptF990Amt>10860387</NoncashContributionsRptF990Amt>
        <MethodOfDeterminingRevenuesTxt>FMV for similar items</MethodOfDeterminingRevenuesTxt>
      </FoodInventoryGrp>
      <DrugsAndMedicalSuppliesGrp>
        <NonCashCheckboxInd>X</NonCashCheckboxInd>
        <ContributionCnt>14</ContributionCnt>
        <NoncashContributionsRptF990Amt>10004792</NoncashContributionsRptF990Amt>
        <MethodOfDeterminingRevenuesTxt>FMV for similar items</MethodOfDeterminingRevenuesTxt>
      </DrugsAndMedicalSuppliesGrp>
      <OtherNonCashContriTableGrp>
        <NonCashCheckboxInd>X</NonCashCheckboxInd>
        <Desc>Hospital equip.</Desc>
        <ContributionCnt>7</ContributionCnt>
        <NoncashContributionsRptF990Amt>511276</NoncashContributionsRptF990Amt>
        <MethodOfDeterminingRevenuesTxt>FMV for similar item</MethodOfDeterminingRevenuesTxt>
      </OtherNonCashContriTableGrp>
      <OtherNonCashContriTableGrp>
        <NonCashCheckboxInd>X</NonCashCheckboxInd>
        <Desc>School suppl.</Desc>
        <ContributionCnt>5</ContributionCnt>
        <NoncashContributionsRptF990Amt>232564</NoncashContributionsRptF990Amt>
        <MethodOfDeterminingRevenuesTxt>FMV for similar item</MethodOfDeterminingRevenuesTxt>
      </OtherNonCashContriTableGrp>
      <Form8283ReceivedCnt>0</Form8283ReceivedCnt>
      <AnyPropertyThatMustBeHeldInd>0</AnyPropertyThatMustBeHeldInd>
      <ReviewProcessUnusualNCGiftsInd>1</ReviewProcessUnusualNCGiftsInd>
      <ThirdPartiesUsedInd>0</ThirdPartiesUsedInd>
      <SupplementalInformationDetail>
        <FormAndLineReferenceDesc>Part I, Column (b):</FormAndLineReferenceDesc>
        <ExplanationTxt>The number of contributions reported is the number of contributions made, not the number of items contributed.</ExplanationTxt>
      </SupplementalInformationDetail>
    </IRS990ScheduleM>
    <IRS990ScheduleO documentId="RetDoc1044400001">
      <SupplementalInformationDetail>
        <FormAndLineReferenceDesc>Form 990, Part I, Line 5, Part V, Line 2a, &amp; Part IX, Lines 7-10:</FormAndLineReferenceDesc>
        <ExplanationTxt>Most salary payments go to non-United States citizens, who are exempt from W-2/W-3 requirements. All United States citizen staff are compensated by a related organization, Food for the Hungry Inc. Food for the Hungry Inc. files all required payroll information returns as required by the IRS. As such, due to common paymaster rules as instructed by the IRS, the number of employees reported represent the number of U.S. employees who work for the filing organization but are compensated by a related organization. The amounts included in 990, Part IX, Lines 7-10 include the salaries and wages for both U.S. and foreign individuals.</ExplanationTxt>
      </SupplementalInformationDetail>
      <SupplementalInformationDetail>
        <FormAndLineReferenceDesc>Form 990, Part VI, Section A, line 1</FormAndLineReferenceDesc>
        <ExplanationTxt>The Executive Committee of the board is comprised of two persons reflecting different constituencies of the whole board. All persons on the Executive Committee are members of the full board. No staff members are members of the Executive Committee. The Executive Committee may exercise the full authority of the board except for actions requiring a majority vote by the full board under California law, actions concerning board or committee membership, changes to the governing documents, any approval of self-dealing transactions, or changes to compensation of top staff or directors.</ExplanationTxt>
      </SupplementalInformationDetail>
      <SupplementalInformationDetail>
        <FormAndLineReferenceDesc>Form 990, Part VI, Section B, line 11b</FormAndLineReferenceDesc>
        <ExplanationTxt>The Form 990 was prepared by an independent CPA firm and was reviewed in detail by the Chief Financial Officer and Director of Finance to verify accuracy. The 990 was then emailed to the board of directors prior to being filed with the IRS.</ExplanationTxt>
      </SupplementalInformationDetail>
      <SupplementalInformationDetail>
        <FormAndLineReferenceDesc>Form 990, Part VI, Section B, line 12c</FormAndLineReferenceDesc>
        <ExplanationTxt>The conflict of interest policy covers top management and members of the board of directors. Individuals are required to sign conflict of interest statements on an annual basis. The corporate secretary reviews the signed statements and monitors transactions for potential conflicts of interest. Should any potential conflicts of interest be disclosed, the board member or officer would be asked to refrain from participation in any deliberation or decision with regard to matters affected by the relationship.</ExplanationTxt>
      </SupplementalInformationDetail>
      <SupplementalInformationDetail>
        <FormAndLineReferenceDesc>Form 990, Part VI, Section B, line 15</FormAndLineReferenceDesc>
        <ExplanationTxt>FH Association does not compensate officers directly. Compensation is paid by Food for the Hungry, Inc., a related organization listed in Schedule R. The board of directors for Food for the Hungry, Inc. is responsible for determining compensation for the organization's officers. When determining an appropriate level of compensation for a given position, the board works closely with the human resources department. Comparability data is collected on salary and benefits offered by similar-sized, like-minded non-profit organizations. This information is used to set a benchmark in determining appropriate compensation to offer. The compensation policy is used to set compensation when an officer is first hired, as well as any time their compensation package is subject to change. All compensation decisions are recorded in documentation held by the Human Resources department. The board approves salaries and benefits in total when it approves the annual budget at its September meeting.</ExplanationTxt>
      </SupplementalInformationDetail>
      <SupplementalInformationDetail>
        <FormAndLineReferenceDesc>Form 990, Part VI, Section C, line 19</FormAndLineReferenceDesc>
        <ExplanationTxt>Food for the Hungry, Inc., a related organization of FH Association, posts FH Association's annual audits on its website at http://fh.org/about/finances. Copies of FH Assocation's tax returns, governing documents, and conflict of interest policy are available to the public upon request.</ExplanationTxt>
      </SupplementalInformationDetail>
      <SupplementalInformationDetail>
        <FormAndLineReferenceDesc>Form 990, Part XI, line 9:</FormAndLineReferenceDesc>
        <ExplanationTxt>Unrealized gain on foreign currency exchange -53,794.</ExplanationTxt>
      </SupplementalInformationDetail>
    </IRS990ScheduleO>
    <IRS990ScheduleR documentId="RetDoc1043400001">
      <IdRelatedTaxExemptOrgGrp>
        <DisregardedEntityName>
          <BusinessNameLine1Txt>Food for the Hungry Inc</BusinessNameLine1Txt>
        </DisregardedEntityName>
        <USAddress>
          <AddressLine1Txt>1224 E Washington Street</AddressLine1Txt>
          <CityNm>Phoenix</CityNm>
          <StateAbbreviationCd>AZ</StateAbbreviationCd>
          <ZIPCd>85034</ZIPCd>
        </USAddress>
        <EIN>952680390</EIN>
        <PrimaryActivitiesTxt>Relief &amp; Development</PrimaryActivitiesTxt>
        <LegalDomicileStateCd>CA</LegalDomicileStateCd>
        <ExemptCodeSectionTxt>501(c)(3)</ExemptCodeSectionTxt>
        <PublicCharityStatusTxt>Line 7</PublicCharityStatusTxt>
        <DirectControllingNACd>N/A</DirectControllingNACd>
        <ControlledOrganizationInd>0</ControlledOrganizationInd>
      </IdRelatedTaxExemptOrgGrp>
      <IdRelatedTaxExemptOrgGrp>
        <DisregardedEntityName>
          <BusinessNameLine1Txt>Food for the Hungry Foundation Inc</BusinessNameLine1Txt>
        </DisregardedEntityName>
        <USAddress>
          <AddressLine1Txt>1224 E Washington Street</AddressLine1Txt>
          <CityNm>Phoenix</CityNm>
          <StateAbbreviationCd>AZ</StateAbbreviationCd>
          <ZIPCd>85034</ZIPCd>
        </USAddress>
        <EIN>680586571</EIN>
        <PrimaryActivitiesTxt>Investment of endowment funds</PrimaryActivitiesTxt>
        <LegalDomicileStateCd>CO</LegalDomicileStateCd>
        <ExemptCodeSectionTxt>501(c)(3)</ExemptCodeSectionTxt>
        <PublicCharityStatusTxt>Line 12b, II</PublicCharityStatusTxt>
        <DirectControllingEntityName>
          <BusinessNameLine1Txt>Food for the Hungry Inc</BusinessNameLine1Txt>
        </DirectControllingEntityName>
        <ControlledOrganizationInd>0</ControlledOrganizationInd>
      </IdRelatedTaxExemptOrgGrp>
      <ReceiptOfIntAnntsRntsRyltsInd>0</ReceiptOfIntAnntsRntsRyltsInd>
      <GiftGrntOrCapContriToOthOrgInd>1</GiftGrntOrCapContriToOthOrgInd>
      <GiftGrntCapContriFromOthOrgInd>1</GiftGrntCapContriFromOthOrgInd>
      <LoansOrGuaranteesToOtherOrgInd>0</LoansOrGuaranteesToOtherOrgInd>
      <LoansOrGuaranteesFromOthOrgInd>0</LoansOrGuaranteesFromOthOrgInd>
      <DivRelatedOrganizationInd>0</DivRelatedOrganizationInd>
      <AssetSaleToOtherOrgInd>0</AssetSaleToOtherOrgInd>
      <AssetPurchaseFromOtherOrgInd>0</AssetPurchaseFromOtherOrgInd>
      <AssetExchangeInd>0</AssetExchangeInd>
      <RentalOfFacilitiesToOthOrgInd>0</RentalOfFacilitiesToOthOrgInd>
      <RentalOfFcltsFromOthOrgInd>0</RentalOfFcltsFromOthOrgInd>
      <PerformOfServicesForOthOrgInd>0</PerformOfServicesForOthOrgInd>
      <PerformOfServicesByOtherOrgInd>0</PerformOfServicesByOtherOrgInd>
      <SharingOfFacilitiesInd>1</SharingOfFacilitiesInd>
      <PaidEmployeesSharingInd>1</PaidEmployeesSharingInd>
      <ReimbursementPaidToOtherOrgInd>0</ReimbursementPaidToOtherOrgInd>
      <ReimbursementPaidByOtherOrgInd>0</ReimbursementPaidByOtherOrgInd>
      <TransferToOtherOrgInd>0</TransferToOtherOrgInd>
      <TransferFromOtherOrgInd>0</TransferFromOtherOrgInd>
      <TransactionsRelatedOrgGrp>
        <OtherOrganizationName>
          <BusinessNameLine1Txt>Food for the Hungry Inc</BusinessNameLine1Txt>
        </OtherOrganizationName>
        <TransactionTypeTxt>B</TransactionTypeTxt>
      </TransactionsRelatedOrgGrp>
      <TransactionsRelatedOrgGrp>
        <OtherOrganizationName>
          <BusinessNameLine1Txt>Food for the Hungry Inc</BusinessNameLine1Txt>
        </OtherOrganizationName>
        <TransactionTypeTxt>C</TransactionTypeTxt>
      </TransactionsRelatedOrgGrp>
      <TransactionsRelatedOrgGrp>
        <OtherOrganizationName>
          <BusinessNameLine1Txt>Food for the Hungry Inc</BusinessNameLine1Txt>
        </OtherOrganizationName>
        <TransactionTypeTxt>N</TransactionTypeTxt>
      </TransactionsRelatedOrgGrp>
      <TransactionsRelatedOrgGrp>
        <OtherOrganizationName>
          <BusinessNameLine1Txt>Food for the Hungry Inc</BusinessNameLine1Txt>
        </OtherOrganizationName>
        <TransactionTypeTxt>O</TransactionTypeTxt>
      </TransactionsRelatedOrgGrp>
    </IRS990ScheduleR>
  </ReturnData>
</Return>